week8/task1_2/my_key_seg1.v
//task1_2 is a part of task1_3, so below is the code of task1_3 
module my_key_seg1(
	input clk,
	input clk1, //for digit
	input rst,
	input [3:0] vl,
	output reg [3:0] hl,
	output reg [3:0] digit,
	output reg[7:0] seg
);

wire [7:0] hl_vl;
reg [15:0] data;
reg [3:0] data_temp;
reg [3:0] current_key;//储存当前按键值
reg key_flag;//按键标志位
reg [1:0] state; 
reg [1:0] state1;

always @(posedge clk1 or posedge rst) begin
	if(rst) begin
		digit = 4'b1111;
		state1 = 2'b00;
		data_temp = 4'b0000;
	end
	else begin
		case (state1)
			2'b00: begin
				data_temp = data[7:4];//???????
				digit = 4'b1110;
				state1 = 2'b01;
			end
			2'b01: begin
                data_temp = data[11:8];
				digit = 4'b1101;
				state1 = 2'b10;
			end
			2'b10: begin
                data_temp = data[15:12];//???????
				digit = 4'b1011;
				state1 = 2'b11;
			end
			2'b11: begin
                data_temp = data[3:0];
				digit = 4'b0111;
				state1 = 2'b00;
			end
			default: begin
				digit = 4'b1111;
				state1 = 2'b00;
                data_temp = 4'b0000;
			end
		endcase
	end
end

always @(posedge clk or posedge rst) begin
    if(rst) begin
        state <= 2'b00; 
		hl <= 4'b1111;
    end
    else begin
        case (state)
            2'b00: begin
				hl <= 4'b1110;
                state <= 2'b01;
            end
            2'b01: begin
				hl <= 4'b1101;
                state <= 2'b10;
            end
            2'b10: begin
				hl <= 4'b1011;
                state <= 2'b11;
            end
            2'b11: begin
				hl <= 4'b0111;
                state <= 2'b00;
            end
            default: begin
				hl <= 4'b1111;
                state <= 2'b00;
            end
        endcase
    end
end 
assign hl_vl = {hl,vl};       

//try to use mealy machine to solve the problem
reg [2:0] FSM_state;
parameter FIRST = 3'b001;
parameter SECOND = 3'b010;
parameter RESULT = 3'b100;
reg [4:0] operator;
parameter OR_OPERATOR = 5'b00001;
parameter AND_OPERATOR = 5'b00010;
parameter ADD_OPERATOR = 5'b00100;
parameter SUB_OPERATOR = 5'b01000;
parameter COMPARE_OPERATOR = 5'b10000;

//the first part of the FSM, trying to get state according to input
reg [11:0] first_num;
reg [11:0] second_num;
reg [15:0] result;
always @(posedge clk, posedge rst) begin
	if(rst) begin
		FSM_state <= FIRST;
		operator <= 5'b00000;
		first_num <= 12'b0000_0000_0000;
		second_num <= 12'b0000_0000_0000;
	end
	else begin
		case(FSM_state)
			FIRST: begin
				if(input_type == NUMBER) begin
					first_num <= {first_num[7:0],input_temp[3:0]};
					FSM_state <= FIRST;
				end
				else if(input_type == OPERATOR) begin
					operator <= input_temp;
					FSM_state <= SECOND;
				end
				else begin
					FSM_state <= FIRST;
				end
			end
			SECOND: begin
				if(input_type == NUMBER) begin
					second_num <= {second_num[7:0],input_temp[3:0]};
					FSM_state <= SECOND;
				end
				else if(input_type == EQUAL) begin
					FSM_state <= RESULT;
				end
				else begin
					FSM_state <= SECOND;
				end
			end
			RESULT: begin
				case(operator)
					OR_OPERATOR: begin
						result <= first_num | second_num;
						FSM_state <= RESULT;
					end
					AND_OPERATOR: begin
						result <= first_num & second_num;
						FSM_state <= RESULT;
					end
					ADD_OPERATOR: begin
						result[3:0] <= (first_num[3:0] + second_num[3:0])%10;
						result[7:4] <= (first_num[7:4] + second_num[7:4] + (first_num[3:0] + second_num[3:0])/10)%10;
						result[11:8] <= (first_num[11:8] + second_num[11:8] + (first_num[7:4] + second_num[7:4] + (first_num[3:0] + second_num[3:0])/10)/10)%10;

						FSM_state <= RESULT;
					end
					SUB_OPERATOR: begin
						result[3:0] <= (first_num[3:0] - second_num[3:0])%10;
						result[7:4] <= (first_num[7:4] - second_num[7:4] + (first_num[3:0] - second_num[3:0])/10)%10;
						result[11:8] <= (first_num[11:8] - second_num[11:8] + (first_num[7:4] - second_num[7:4] + (first_num[3:0] - second_num[3:0])/10)/10)%10;
						FSM_state <= RESULT;
					end
					COMPARE_OPERATOR: begin
						if(first_num > second_num) begin
							result <= 12'b1;
						end
						else begin
							result <= 12'b0;
						end
						FSM_state <= RESULT;
					end
					default: begin
						result <= 12'b0;
						FSM_state <= RESULT;
					end
				endcase
			end
			default: begin
				FSM_state <= FIRST;
			end
	endcase
	end
end

//process the origin input to a simple one
reg [2:0] input_type;
parameter NUMBER = 3'b001;
parameter OPERATOR = 3'b010;
parameter EQUAL = 3'b100;

reg [4:0] input_temp;

always @ (posedge clk,posedge rst) begin
	if (rst) begin
		input_type <= 3'b000;
		input_temp <= 5'b00000;
	end
	else begin
		case (hl_vl)
			8'b0111_0111: begin
				//for =  
				input_type <= EQUAL;
				input_temp <= 5'b00000;   
			end
			8'b1011_0111: begin
				//for and   
				input_type <= OPERATOR;
				input_temp <= AND_OPERATOR;
			end
			8'b1101_0111: begin
				//for 0
				input_type <= NUMBER;
				input_temp <= 5'b00000;
			end
			8'b1110_0111: begin
				//for or     
				input_type <= OPERATOR;
				input_temp <= OR_OPERATOR;
			end
			8'b0111_1011: begin
				//for +     
				input_type <= OPERATOR;
				input_temp <= ADD_OPERATOR;
			end
			8'b1011_1011: begin
				//for 3
				input_type <= NUMBER;
				input_temp <= 5'b00011;
			end
			8'b1101_1011: begin
				//for 2
				input_type <= NUMBER;
				input_temp <= 5'b00010;
			end
			8'b1110_1011: begin
				//for 1
				input_type <= NUMBER;
				input_temp <= 5'b00001;
			end
			8'b0111_1101: begin      
				//for -     
				input_type <= OPERATOR;
				input_temp <= SUB_OPERATOR;
			end
			8'b1011_1101: begin
				//for 6
				input_type <= NUMBER;
				input_temp <= 5'b00110;
			end
			8'b1101_1101: begin
				//for 5
				input_type <= NUMBER;
				input_temp <= 5'b00101;
			end
			8'b1110_1101: begin
				//for 4
				input_type <= NUMBER;
				input_temp <= 5'b00100;
			end
			8'b0111_1110: begin      
				//for compare
				input_type <= OPERATOR;
				input_temp <= COMPARE_OPERATOR;
			end
			8'b1011_1110: begin
				//for 9
				input_type <= NUMBER;
				input_temp <= 5'b01001;
			end
			8'b1101_1110: begin
				//for 8
				input_type <= NUMBER;
				input_temp <= 5'b01000;
			end
			8'b1110_1110: begin
				//for 7
				input_type <= NUMBER;
				input_temp <= 5'b00111;
			end
			default: begin
				input_type <= 3'b000;
				input_temp <= 5'b00000;
			end
		endcase
	end
end

//the second part of the FSM, trying to show the result according to the state
always @(posedge clk, posedge rst) begin
	if(rst) begin
		data <= 16'b0000_0000_0000_0000;
	end
	else begin
		case(FSM_state)
			FIRST: begin
				data <= first_num;
			end
			SECOND: begin
				data <= second_num;
			end
			RESULT: begin
				data <= result;
			end
			default: begin
				data <= 16'b0000_0000_0000_0000;
			end
		endcase
	end
end

always @(posedge clk1, posedge rst) begin
	if(rst) begin
		seg = 8'hc0;
	end
	else begin
		case (data_temp)
			0: seg = 8'hc0;
			1: seg = 8'hf9;
			2: seg = 8'ha4;
			3: seg = 8'hb0;
			4: seg = 8'h99;
			5: seg = 8'h92;
			6: seg = 8'h82;
			7: seg = 8'hf8;
			8: seg = 8'h80;
			9: seg = 8'h90;
			10: seg = 8'h88;
			11: seg = 8'h83;
			12: seg = 8'hc6;
			13: seg = 8'ha1;
			14: seg = 8'h86;
			15: seg = 8'h8e;
			default: seg = 8'hc0;
		endcase
	end
end

endmodule

week8/task1_2/my_key_fre_div.v
`define CNT_MAX 10
`define CNT_MAX1 25

module my_key_fre_div(
	input clk,
	input rst,
	output reg clk_div_out,
	output reg clk_div_out1
);

reg [31:0] div_cnt;

always @ (posedge clk,posedge rst) begin
	if (rst) begin
	  	div_cnt <= 0;
		clk_div_out <= 0;
	end
	else if (div_cnt == `CNT_MAX-1) begin
		clk_div_out <= ~clk_div_out; //clk = 25MH, 25Hz
		div_cnt <= 0;
	end
	else
		div_cnt <= div_cnt + 1'b1;
end

reg [31:0] div_cnt1;
always @ (posedge clk,posedge rst) begin
	if (rst) begin
	  	div_cnt1 <= 0;
		clk_div_out1 <= 0;
	end
	else if (div_cnt1 == `CNT_MAX1-1) begin
		clk_div_out1 <= ~clk_div_out1;
		div_cnt1 <= 0;
	end
	else
		div_cnt1 <= div_cnt1 + 1'b1;
end


endmodule

week8/task1_2/task1_2_top.v
`include "my_key_seg1.v"
`include "my_key_fre_div.v"
module task1_2_top(
    input clk,
    input rst,
    input [3:0] vl,
    output [3:0] hl,
    output [3:0] digit,
    output [7:0] seg
);

wire clk_div_out;
wire clk_div_out1;
my_key_fre_div uut_fre_div(
    .clk(clk),
    .rst(rst),
    .clk_div_out(clk_div_out),
    .clk_div_out1(clk_div_out1)

);
my_key_seg1 uut_my_key_seg(
    .clk(clk_div_out),
    .clk1(clk_div_out1),
    .rst(rst),
    .vl(vl),
    .hl(hl),
    .digit(digit),
    .seg(seg)
);


endmodule

week8/task1_2/tb_task1_2.v
//~ `New testbench
`timescale 1ns/1ps
`include "task1_2_top.v"

module tb_task1_2_top;

    // task1_2_top Parameters
    parameter PERIOD = 10;

    // task1_2_top Inputs
    reg [3:0] vl = 0;
    reg clk = 0;
    reg rst = 0;

    // task1_2_top Outputs
    wire [3:0] hl;
    wire [3:0] digit;
    wire [7:0] seg;

    task1_2_top u_task1_2_top (
        .clk(clk),
        .rst(rst),
        .vl(vl[3:0]),
        .hl(hl[3:0]),
        .digit(digit[3:0]),
        .seg(seg[7:0])
    );

    initial begin
        $dumpfile(".\\wave\\tb_task1_2_top.vcd");
        $dumpvars(0, tb_task1_2_top);
        clk = 0;
        rst = 0;
        vl = 4'b1111;
        rst = 1;
        #10
        rst = 0;
        #500
        $finish;
    end

    always begin
        #1 clk = ~clk;
    end

    always begin
        #100
        vl = 4'b1110;
        #100
        vl = 4'b1101;
        #100
        vl = 4'b1011;
        #100
        vl = 4'b0111;
    end

endmodule

week8/task1_2/wave/tb_task1_2_top.vcd
$date
	Sun Nov 19 18:26:21 2023
$end
$version
	Icarus Verilog
$end
$timescale
	1ps
$end
$scope module tb_task1_2_top $end
$var wire 8 ! seg [7:0] $end
$var wire 4 " hl [3:0] $end
$var wire 4 # digit [3:0] $end
$var parameter 32 $ PERIOD $end
$var reg 1 % clk $end
$var reg 1 & rst $end
$var reg 4 ' vl [3:0] $end
$scope module u_task1_2_top $end
$var wire 1 % clk $end
$var wire 1 & rst $end
$var wire 4 ( vl [3:0] $end
$var wire 8 ) seg [7:0] $end
$var wire 4 * hl [3:0] $end
$var wire 4 + digit [3:0] $end
$var wire 1 , clk_div_out1 $end
$var wire 1 - clk_div_out $end
$scope module uut_fre_div $end
$var wire 1 % clk $end
$var wire 1 & rst $end
$var reg 1 - clk_div_out $end
$var reg 1 , clk_div_out1 $end
$var reg 32 . div_cnt [31:0] $end
$var reg 32 / div_cnt1 [31:0] $end
$upscope $end
$scope module uut_my_key_seg $end
$var wire 1 - clk $end
$var wire 1 , clk1 $end
$var wire 1 & rst $end
$var wire 4 0 vl [3:0] $end
$var wire 8 1 hl_vl [7:0] $end
$var parameter 5 2 ADD_OPERATOR $end
$var parameter 5 3 AND_OPERATOR $end
$var parameter 5 4 COMPARE_OPERATOR $end
$var parameter 3 5 EQUAL $end
$var parameter 3 6 FIRST $end
$var parameter 3 7 NUMBER $end
$var parameter 3 8 OPERATOR $end
$var parameter 5 9 OR_OPERATOR $end
$var parameter 3 : RESULT $end
$var parameter 3 ; SECOND $end
$var parameter 5 < SUB_OPERATOR $end
$var reg 3 = FSM_state [2:0] $end
$var reg 16 > data [15:0] $end
$var reg 4 ? data_temp [3:0] $end
$var reg 4 @ digit [3:0] $end
$var reg 12 A first_num [11:0] $end
$var reg 4 B hl [3:0] $end
$var reg 5 C input_temp [4:0] $end
$var reg 3 D input_type [2:0] $end
$var reg 5 E operator [4:0] $end
$var reg 16 F result [15:0] $end
$var reg 12 G second_num [11:0] $end
$var reg 8 H seg [7:0] $end
$var reg 2 I state [1:0] $end
$var reg 2 J state1 [1:0] $end
$upscope $end
$upscope $end
$upscope $end
$enddefinitions $end
$comment Show the parameter values. $end
$dumpall
b1000 <
b10 ;
b100 :
b1 9
b10 8
b1 7
b1 6
b100 5
b10000 4
b10 3
b100 2
b1010 $
$end
#0
$dumpvars
b0 J
b0 I
b11000000 H
b0 G
bx F
b0 E
b0 D
b0 C
b1111 B
b0 A
b1111 @
b0 ?
b0 >
b1 =
b11111111 1
b1111 0
b0 /
b0 .
0-
0,
b1111 +
b1111 *
b11000000 )
b1111 (
b1111 '
1&
0%
b1111 #
b1111 "
b11000000 !
$end
#1000
1%
#2000
0%
#3000
1%
#4000
0%
#5000
1%
#6000
0%
#7000
1%
#8000
0%
#9000
1%
#10000
0%
0&
#11000
b1 .
b1 /
1%
#12000
0%
#13000
b10 /
b10 .
1%
#14000
0%
#15000
b11 .
b11 /
1%
#16000
0%
#17000
b100 /
b100 .
1%
#18000
0%
#19000
b101 .
b101 /
1%
#20000
0%
#21000
b110 /
b110 .
1%
#22000
0%
#23000
b111 .
b111 /
1%
#24000
0%
#25000
b1000 /
b1000 .
1%
#26000
0%
#27000
b1001 .
b1001 /
1%
#28000
0%
#29000
b1 I
b11101111 1
b1110 "
b1110 *
b1110 B
b1010 /
b0 .
1-
1%
#30000
0%
#31000
b1 .
b1011 /
1%
#32000
0%
#33000
b1100 /
b10 .
1%
#34000
0%
#35000
b11 .
b1101 /
1%
#36000
0%
#37000
b1110 /
b100 .
1%
#38000
0%
#39000
b101 .
b1111 /
1%
#40000
0%
#41000
b10000 /
b110 .
1%
#42000
0%
#43000
b111 .
b10001 /
1%
#44000
0%
#45000
b10010 /
b1000 .
1%
#46000
0%
#47000
b1001 .
b10011 /
1%
#48000
0%
#49000
b10100 /
b0 .
0-
1%
#50000
0%
#51000
b1 .
b10101 /
1%
#52000
0%
#53000
b10110 /
b10 .
1%
#54000
0%
#55000
b11 .
b10111 /
1%
#56000
0%
#57000
b11000 /
b100 .
1%
#58000
0%
#59000
b1 J
b1110 #
b1110 +
b1110 @
b101 .
b0 /
1,
1%
#60000
0%
#61000
b1 /
b110 .
1%
#62000
0%
#63000
b111 .
b10 /
1%
#64000
0%
#65000
b11 /
b1000 .
1%
#66000
0%
#67000
b1001 .
b100 /
1%
#68000
0%
#69000
b10 I
b11011111 1
b1101 "
b1101 *
b1101 B
b101 /
b0 .
1-
1%
#70000
0%
#71000
b1 .
b110 /
1%
#72000
0%
#73000
b111 /
b10 .
1%
#74000
0%
#75000
b11 .
b1000 /
1%
#76000
0%
#77000
b1001 /
b100 .
1%
#78000
0%
#79000
b101 .
b1010 /
1%
#80000
0%
#81000
b1011 /
b110 .
1%
#82000
0%
#83000
b111 .
b1100 /
1%
#84000
0%
#85000
b1101 /
b1000 .
1%
#86000
0%
#87000
b1001 .
b1110 /
1%
#88000
0%
#89000
b1111 /
b0 .
0-
1%
#90000
0%
#91000
b1 .
b10000 /
1%
#92000
0%
#93000
b10001 /
b10 .
1%
#94000
0%
#95000
b11 .
b10010 /
1%
#96000
0%
#97000
b10011 /
b100 .
1%
#98000
0%
#99000
b101 .
b10100 /
1%
#100000
0%
b11011110 1
b1110 '
b1110 (
b1110 0
#101000
b10101 /
b110 .
1%
#102000
0%
#103000
b111 .
b10110 /
1%
#104000
0%
#105000
b10111 /
b1000 .
1%
#106000
0%
#107000
b1001 .
b11000 /
1%
#108000
0%
#109000
b1000 C
b1 D
b11 I
b10111110 1
b1011 "
b1011 *
b1011 B
b0 /
0,
b0 .
1-
1%
#110000
0%
#111000
b1 .
b1 /
1%
#112000
0%
#113000
b10 /
b10 .
1%
#114000
0%
#115000
b11 .
b11 /
1%
#116000
0%
#117000
b100 /
b100 .
1%
#118000
0%
#119000
b101 .
b101 /
1%
#120000
0%
#121000
b110 /
b110 .
1%
#122000
0%
#123000
b111 .
b111 /
1%
#124000
0%
#125000
b1000 /
b1000 .
1%
#126000
0%
#127000
b1001 .
b1001 /
1%
#128000
0%
#129000
b1010 /
b0 .
0-
1%
#130000
0%
#131000
b1 .
b1011 /
1%
#132000
0%
#133000
b1100 /
b10 .
1%
#134000
0%
#135000
b11 .
b1101 /
1%
#136000
0%
#137000
b1110 /
b100 .
1%
#138000
0%
#139000
b101 .
b1111 /
1%
#140000
0%
#141000
b10000 /
b110 .
1%
#142000
0%
#143000
b111 .
b10001 /
1%
#144000
0%
#145000
b10010 /
b1000 .
1%
#146000
0%
#147000
b1001 .
b10011 /
1%
#148000
0%
#149000
b0 I
b1111110 1
b111 "
b111 *
b111 B
b1000 A
b1001 C
b10100 /
b0 .
1-
1%
#150000
0%
#151000
b1 .
b10101 /
1%
#152000
0%
#153000
b10110 /
b10 .
1%
#154000
0%
#155000
b11 .
b10111 /
1%
#156000
0%
#157000
b11000 /
b100 .
1%
#158000
0%
#159000
b10 J
b1101 #
b1101 +
b1101 @
b101 .
b0 /
1,
1%
#160000
0%
#161000
b1 /
b110 .
1%
#162000
0%
#163000
b111 .
b10 /
1%
#164000
0%
#165000
b11 /
b1000 .
1%
#166000
0%
#167000
b1001 .
b100 /
1%
#168000
0%
#169000
b101 /
b0 .
0-
1%
#170000
0%
#171000
b1 .
b110 /
1%
#172000
0%
#173000
b111 /
b10 .
1%
#174000
0%
#175000
b11 .
b1000 /
1%
#176000
0%
#177000
b1001 /
b100 .
1%
#178000
0%
#179000
b101 .
b1010 /
1%
#180000
0%
#181000
b1011 /
b110 .
1%
#182000
0%
#183000
b111 .
b1100 /
1%
#184000
0%
#185000
b1101 /
b1000 .
1%
#186000
0%
#187000
b1001 .
b1110 /
1%
#188000
0%
#189000
b1000 >
b10000 C
b10 D
b10001001 A
b1 I
b11101110 1
b1110 "
b1110 *
b1110 B
b1111 /
b0 .
1-
1%
#190000
0%
#191000
b1 .
b10000 /
1%
#192000
0%
#193000
b10001 /
b10 .
1%
#194000
0%
#195000
b11 .
b10010 /
1%
#196000
0%
#197000
b10011 /
b100 .
1%
#198000
0%
#199000
b101 .
b10100 /
1%
#200000
0%
b11101101 1
b1101 '
b1101 (
b1101 0
#201000
b10101 /
b110 .
1%
#202000
0%
#203000
b111 .
b10110 /
1%
#204000
0%
#205000
b10111 /
b1000 .
1%
#206000
0%
#207000
b1001 .
b11000 /
1%
#208000
0%
#209000
b0 /
0,
b0 .
0-
1%
#210000
0%
#211000
b1 .
b1 /
1%
#212000
0%
#213000
b10 /
b10 .
1%
#214000
0%
#215000
b11 .
b11 /
1%
#216000
0%
#217000
b100 /
b100 .
1%
#218000
0%
#219000
b101 .
b101 /
1%
#220000
0%
#221000
b110 /
b110 .
1%
#222000
0%
#223000
b111 .
b111 /
1%
#224000
0%
#225000
b1000 /
b1000 .
1%
#226000
0%
#227000
b1001 .
b1001 /
1%
#228000
0%
#229000
b10 I
b11011101 1
b1101 "
b1101 *
b1101 B
b10 =
b10000 E
b100 C
b1 D
b10001001 >
b1010 /
b0 .
1-
1%
#230000
0%
#231000
b1 .
b1011 /
1%
#232000
0%
#233000
b1100 /
b10 .
1%
#234000
0%
#235000
b11 .
b1101 /
1%
#236000
0%
#237000
b1110 /
b100 .
1%
#238000
0%
#239000
b101 .
b1111 /
1%
#240000
0%
#241000
b10000 /
b110 .
1%
#242000
0%
#243000
b111 .
b10001 /
1%
#244000
0%
#245000
b10010 /
b1000 .
1%
#246000
0%
#247000
b1001 .
b10011 /
1%
#248000
0%
#249000
b10100 /
b0 .
0-
1%
#250000
0%
#251000
b1 .
b10101 /
1%
#252000
0%
#253000
b10110 /
b10 .
1%
#254000
0%
#255000
b11 .
b10111 /
1%
#256000
0%
#257000
b11000 /
b100 .
1%
#258000
0%
#259000
b11 J
b1011 #
b1011 +
b1011 @
b101 .
b0 /
1,
1%
#260000
0%
#261000
b1 /
b110 .
1%
#262000
0%
#263000
b111 .
b10 /
1%
#264000
0%
#265000
b11 /
b1000 .
1%
#266000
0%
#267000
b1001 .
b100 /
1%
#268000
0%
#269000
b0 >
b101 C
b100 G
b11 I
b10111101 1
b1011 "
b1011 *
b1011 B
b101 /
b0 .
1-
1%
#270000
0%
#271000
b1 .
b110 /
1%
#272000
0%
#273000
b111 /
b10 .
1%
#274000
0%
#275000
b11 .
b1000 /
1%
#276000
0%
#277000
b1001 /
b100 .
1%
#278000
0%
#279000
b101 .
b1010 /
1%
#280000
0%
#281000
b1011 /
b110 .
1%
#282000
0%
#283000
b111 .
b1100 /
1%
#284000
0%
#285000
b1101 /
b1000 .
1%
#286000
0%
#287000
b1001 .
b1110 /
1%
#288000
0%
#289000
b1111 /
b0 .
0-
1%
#290000
0%
#291000
b1 .
b10000 /
1%
#292000
0%
#293000
b10001 /
b10 .
1%
#294000
0%
#295000
b11 .
b10010 /
1%
#296000
0%
#297000
b10011 /
b100 .
1%
#298000
0%
#299000
b101 .
b10100 /
1%
#300000
0%
b10111011 1
b1011 '
b1011 (
b1011 0
#301000
b10101 /
b110 .
1%
#302000
0%
#303000
b111 .
b10110 /
1%
#304000
0%
#305000
b10111 /
b1000 .
1%
#306000
0%
#307000
b1001 .
b11000 /
1%
#308000
0%
#309000
b0 I
b1111011 1
b111 "
b111 *
b111 B
b1000101 G
b11 C
b100 >
b0 /
0,
b0 .
1-
1%
#310000
0%
#311000
b1 .
b1 /
1%
#312000
0%
#313000
b10 /
b10 .
1%
#314000
0%
#315000
b11 .
b11 /
1%
#316000
0%
#317000
b100 /
b100 .
1%
#318000
0%
#319000
b101 .
b101 /
1%
#320000
0%
#321000
b110 /
b110 .
1%
#322000
0%
#323000
b111 .
b111 /
1%
#324000
0%
#325000
b1000 /
b1000 .
1%
#326000
0%
#327000
b1001 .
b1001 /
1%
#328000
0%
#329000
b1010 /
b0 .
0-
1%
#330000
0%
#331000
b1 .
b1011 /
1%
#332000
0%
#333000
b1100 /
b10 .
1%
#334000
0%
#335000
b11 .
b1101 /
1%
#336000
0%
#337000
b1110 /
b100 .
1%
#338000
0%
#339000
b101 .
b1111 /
1%
#340000
0%
#341000
b10000 /
b110 .
1%
#342000
0%
#343000
b111 .
b10001 /
1%
#344000
0%
#345000
b10010 /
b1000 .
1%
#346000
0%
#347000
b1001 .
b10011 /
1%
#348000
0%
#349000
b1000101 >
b100 C
b10 D
b10001010011 G
b1 I
b11101011 1
b1110 "
b1110 *
b1110 B
b10100 /
b0 .
1-
1%
#350000
0%
#351000
b1 .
b10101 /
1%
#352000
0%
#353000
b10110 /
b10 .
1%
#354000
0%
#355000
b11 .
b10111 /
1%
#356000
0%
#357000
b11000 /
b100 .
1%
#358000
0%
#359000
b0 J
b111 #
b111 +
b111 @
b101 ?
b101 .
b0 /
1,
1%
#360000
0%
#361000
b1 /
b110 .
1%
#362000
0%
#363000
b111 .
b10 /
1%
#364000
0%
#365000
b11 /
b1000 .
1%
#366000
0%
#367000
b1001 .
b100 /
1%
#368000
0%
#369000
b101 /
b0 .
0-
1%
#370000
0%
#371000
b1 .
b110 /
1%
#372000
0%
#373000
b111 /
b10 .
1%
#374000
0%
#375000
b11 .
b1000 /
1%
#376000
0%
#377000
b1001 /
b100 .
1%
#378000
0%
#379000
b101 .
b1010 /
1%
#380000
0%
#381000
b1011 /
b110 .
1%
#382000
0%
#383000
b111 .
b1100 /
1%
#384000
0%
#385000
b1101 /
b1000 .
1%
#386000
0%
#387000
b1001 .
b1110 /
1%
#388000
0%
#389000
b10 I
b11011011 1
b1101 "
b1101 *
b1101 B
b1 C
b1 D
b10001010011 >
b1111 /
b0 .
1-
1%
#390000
0%
#391000
b1 .
b10000 /
1%
#392000
0%
#393000
b10001 /
b10 .
1%
#394000
0%
#395000
b11 .
b10010 /
1%
#396000
0%
#397000
b10011 /
b100 .
1%
#398000
0%
#399000
b101 .
b10100 /
1%
#400000
0%
b11010111 1
b111 '
b111 (
b111 0
#401000
b10101 /
b110 .
1%
#402000
0%
#403000
b111 .
b10110 /
1%
#404000
0%
#405000
b10111 /
b1000 .
1%
#406000
0%
#407000
b1001 .
b11000 /
1%
#408000
0%
#409000
b0 /
0,
b0 .
0-
1%
#410000
0%
#411000
b1 .
b1 /
1%
#412000
0%
#413000
b10 /
b10 .
1%
#414000
0%
#415000
b11 .
b11 /
1%
#416000
0%
#417000
b100 /
b100 .
1%
#418000
0%
#419000
b101 .
b101 /
1%
#420000
0%
#421000
b110 /
b110 .
1%
#422000
0%
#423000
b111 .
b111 /
1%
#424000
0%
#425000
b1000 /
b1000 .
1%
#426000
0%
#427000
b1001 .
b1001 /
1%
#428000
0%
#429000
b0 C
b10100110001 G
b11 I
b10110111 1
b1011 "
b1011 *
b1011 B
b1010 /
b0 .
1-
1%
#430000
0%
#431000
b1 .
b1011 /
1%
#432000
0%
#433000
b1100 /
b10 .
1%
#434000
0%
#435000
b11 .
b1101 /
1%
#436000
0%
#437000
b1110 /
b100 .
1%
#438000
0%
#439000
b101 .
b1111 /
1%
#440000
0%
#441000
b10000 /
b110 .
1%
#442000
0%
#443000
b111 .
b10001 /
1%
#444000
0%
#445000
b10010 /
b1000 .
1%
#446000
0%
#447000
b1001 .
b10011 /
1%
#448000
0%
#449000
b10100 /
b0 .
0-
1%
#450000
0%
#451000
b1 .
b10101 /
1%
#452000
0%
#453000
b10110 /
b10 .
1%
#454000
0%
#455000
b11 .
b10111 /
1%
#456000
0%
#457000
b11000 /
b100 .
1%
#458000
0%
#459000
b10010010 !
b10010010 )
b10010010 H
b1 J
b1110 #
b1110 +
b1110 @
b101 .
b0 /
1,
1%
#460000
0%
#461000
b1 /
b110 .
1%
#462000
0%
#463000
b111 .
b10 /
1%
#464000
0%
#465000
b11 /
b1000 .
1%
#466000
0%
#467000
b1001 .
b100 /
1%
#468000
0%
#469000
b0 I
b1110111 1
b111 "
b111 *
b111 B
b1100010000 G
b10 C
b10 D
b10100110001 >
b101 /
b0 .
1-
1%
#470000
0%
#471000
b1 .
b110 /
1%
#472000
0%
#473000
b111 /
b10 .
1%
#474000
0%
#475000
b11 .
b1000 /
1%
#476000
0%
#477000
b1001 /
b100 .
1%
#478000
0%
#479000
b101 .
b1010 /
1%
#480000
0%
#481000
b1011 /
b110 .
1%
#482000
0%
#483000
b111 .
b1100 /
1%
#484000
0%
#485000
b1101 /
b1000 .
1%
#486000
0%
#487000
b1001 .
b1110 /
1%
#488000
0%
#489000
b1111 /
b0 .
0-
1%
#490000
0%
#491000
b1 .
b10000 /
1%
#492000
0%
#493000
b10001 /
b10 .
1%
#494000
0%
#495000
b11 .
b10010 /
1%
#496000
0%
#497000
b10011 /
b100 .
1%
#498000
0%
#499000
b101 .
b10100 /
1%
#500000
0%
b1111110 1
b1110 '
b1110 (
b1110 0
#501000
b10101 /
b110 .
1%
#502000
0%
#503000
b111 .
b10110 /
1%
#504000
0%
#505000
b10111 /
b1000 .
1%
#506000
0%
#507000
b1001 .
b11000 /
1%
#508000
0%
#509000
b1100010000 >
b10000 C
b1 I
b11101110 1
b1110 "
b1110 *
b1110 B
b0 /
0,
b0 .
1-
1%
