week6/task2_2.v
//这玩意倒是可以完全照抄task1_3，验证这个没问题，1_3应该也没问题
`define CNT_MAX 32'd2500000
module task2_2(
    input clk,
    input reset,
    input button_io,
    output reg clk_div,
    output reg [3:0] digit, //这里的digit是一个4位的寄存器，储存当前显示的数码管的位数
    output reg [7:0] segment //这里的segment是一个8位的寄存器，用于驱动数码管
);
localparam SIMULATION_PARAMETER = 32'd100000; //仿真缩小时间尺度，实机为1

reg [15:0] data;//这里的data是一个16位的寄存器，储存数码管的值
reg [3:0] data_temp; //存储当前显示的数码管的值


reg pulse1, pulse2, pulse3;
always @(posedge clk, posedge reset) begin
    //这里实现了按键的下降沿检测
    if(reset)
    begin 
        pulse1 <= 1'b0;
        pulse2 <= 1'b0;
        pulse3 <= 1'b0;
    end
    else
    begin
        pulse1 <= button_io;
        pulse2 <= pulse1;
        pulse3 <= pulse2;
    end
end
wire button_negedge = ~pulse2 & pulse3;
wire button_posedge = pulse2 & ~pulse3;

reg [31:0] div_reg;
always @ (posedge clk or posedge reset) begin
    //这里实现了一个1Hz的计数器
    if(reset)
    begin
        div_reg <= 32'b0;
        clk_div <= 1'b0;
    end

    else
    begin
        if(div_reg < 32'd12500)
            div_reg <= div_reg + 32'b1;
        else
        begin
            div_reg <= 32'b0;
            clk_div <= ~clk_div;
        end
    end
end
reg [31:0] cnt;
always @ (posedge clk or posedge reset)begin
    //这里实现了按键的延时
    if(reset) begin
        cnt <= 32'b0;
        data <= 16'b0000_0000_0000_0000;
    end
    else if(delay_flag) begin
        if(cnt == `CNT_MAX-1) begin //这里要加个`是真的逆天
            if(button_io == 1'b1) begin
                //感觉不太合规，但是少两个always
                data <= data + 16'b0000_0000_0000_0001;
            end
            cnt <= 32'b0;
        end
        else begin
            cnt <= cnt + 32'b1;
        end
    end
end

reg delay_flag;
always @(posedge clk or posedge reset) begin
    if(reset) begin
        delay_flag <= 1'b0;
    end
    else if(button_posedge) begin
        delay_flag <= 1'b1;
    end
    else if(cnt == `CNT_MAX-1) begin
        delay_flag <= 1'b0;
    end
end

reg [1:0] state; 
always @(posedge clk_div or posedge reset) begin
    //不分频有bug，分频之后就没问题了
    if(reset) begin
        data_temp = 4'b0000;
        digit = 4'b1111;
        state = 2'b00; 
    end
    else begin
        case (state)
            2'b00: begin
                digit = 4'b1110;
                data_temp = data[15:12];
                state = 2'b01;
            end
            2'b01: begin
                digit = 4'b1101;
                data_temp = data[11:8];
                state = 2'b10;
            end
            2'b10: begin
                digit = 4'b1011;
                data_temp = data[7:4];
                state = 2'b11;
            end
            2'b11: begin
                digit = 4'b0111;
                data_temp = data[3:0];
                state = 2'b00;
            end
            default: begin
                digit = 4'b1111;
                data_temp = 4'b0000;
                state = 2'b00;
            end
        endcase
    end
end

always @(posedge clk, posedge reset) begin
    if(reset) begin
        segment = 8'h00;
    end
    else begin
        case (data_temp)
            0: segment = 8'hc0;
            1: segment = 8'hf9;
            2: segment = 8'ha4;
            3: segment = 8'hb0;
            4: segment = 8'h99;
            5: segment = 8'h92;
            6: segment = 8'h82;
            7: segment = 8'hf8;
            8: segment = 8'h80;
            9: segment = 8'h90;
            10: segment = 8'h88;
            11: segment = 8'h83;
            12: segment = 8'hc6;
            13: segment = 8'ha1;
            14: segment = 8'h86;
            15: segment = 8'h8e;
            default: segment = 8'h00;
        endcase
    end
end
endmodule

week6/tb_task2_2.v
//~ `New testbench
`timescale 1ns/1ps
`include "task2_2.v"
module tb_task2_2;

    // task2_2 Parameters
    parameter PERIOD = 10;

    // task2_2 Inputs
    reg clk = 0;
    reg reset = 0;
    reg button_io = 0;

    // task2_2 Outputs
    wire [3:0] digit;
    wire [7:0] segment;

    task2_2 u_task2_2 (
        .clk (clk),
        .reset (reset),
        .button_io (button_io),
        .digit (digit[3:0]),
        .segment (segment[7:0])
    );

    initial begin
        $dumpfile(".//wave//tb_task2_2.vcd");
        $dumpvars(0, tb_task2_2);
        
        // Initialize Inputs
        clk = 0;
        reset = 0;
        button_io = 0;
        reset = 1;
        #10
        reset = 0;
        #10000;
        $finish;
    end
    always begin
        #0.1 clk = ~clk;
    end
    always begin
        #1 button_io = 1;
        #10 button_io = 0;
    end

endmodule

week6/wave/tb_task2_2.vcd
$date
	Fri Nov 10 10:21:14 2023
$end
$version
	Icarus Verilog
$end
$timescale
	1ps
$end
$scope module tb_task2_2 $end
$var wire 8 ! segment [7:0] $end
$var wire 4 " digit [3:0] $end
$var parameter 32 # PERIOD $end
$var reg 1 $ button_io $end
$var reg 1 % clk $end
$var reg 1 & reset $end
$scope module u_task2_2 $end
$var wire 1 $ button_io $end
$var wire 1 ' button_negedge $end
$var wire 1 ( button_posedge $end
$var wire 1 % clk $end
$var wire 1 & reset $end
$var parameter 32 ) SIMULATION_PARAMETER $end
$var reg 1 * clk_div $end
$var reg 32 + cnt [31:0] $end
$var reg 16 , data [15:0] $end
$var reg 4 - data_temp [3:0] $end
$var reg 1 . delay_flag $end
$var reg 4 / digit [3:0] $end
$var reg 32 0 div_reg [31:0] $end
$var reg 1 1 pulse1 $end
$var reg 1 2 pulse2 $end
$var reg 1 3 pulse3 $end
$var reg 8 4 segment [7:0] $end
$var reg 2 5 state [1:0] $end
$upscope $end
$upscope $end
$enddefinitions $end
$comment Show the parameter values. $end
$dumpall
b11000011010100000 )
b1010 #
$end
#0
$dumpvars
b0 5
b0 4
03
02
01
b0 0
b1111 /
0.
b0 -
b0 ,
b0 +
0*
0(
0'
1&
0%
0$
b1111 "
b0 !
$end
#100
1%
#200
0%
#300
1%
#400
0%
#500
1%
#600
0%
#700
1%
#800
0%
#900
1%
#1000
0%
1$
#1100
1%
#1200
0%
#1300
1%
#1400
0%
#1500
1%
#1600
0%
#1700
1%
#1800
0%
#1900
1%
#2000
0%
#2100
1%
#2200
0%
#2300
1%
#2400
0%
#2500
1%
#2600
0%
#2700
1%
#2800
0%
#2900
1%
#3000
0%
#3100
1%
#3200
0%
#3300
1%
#3400
0%
#3500
1%
#3600
0%
#3700
1%
#3800
0%
#3900
1%
#4000
0%
#4100
1%
#4200
0%
#4300
1%
#4400
0%
#4500
1%
#4600
0%
#4700
1%
#4800
0%
#4900
1%
#5000
0%
#5100
1%
#5200
0%
#5300
1%
#5400
0%
#5500
1%
#5600
0%
#5700
1%
#5800
0%
#5900
1%
#6000
0%
#6100
1%
#6200
0%
#6300
1%
#6400
0%
#6500
1%
#6600
0%
#6700
1%
#6800
0%
#6900
1%
#7000
0%
#7100
1%
#7200
0%
#7300
1%
#7400
0%
#7500
1%
#7600
0%
#7700
1%
#7800
0%
#7900
1%
#8000
0%
#8100
1%
#8200
0%
#8300
1%
#8400
0%
#8500
1%
#8600
0%
#8700
1%
#8800
0%
#8900
1%
#9000
0%
#9100
1%
#9200
0%
#9300
1%
#9400
0%
#9500
1%
#9600
0%
#9700
1%
#9800
0%
#9900
1%
#10000
0%
0&
#10100
b1 0
11
b11000000 !
b11000000 4
1%
#10200
0%
#10300
1(
12
b10 0
1%
#10400
0%
#10500
0(
1.
b11 0
13
1%
#10600
0%
#10700
b100 0
b1 +
1%
#10800
0%
#10900
b10 +
b101 0
1%
#11000
0%
0$
#11100
01
b110 0
b11 +
1%
#11200
0%
#11300
1'
b100 +
b111 0
02
1%
#11400
0%
#11500
0'
03
b1000 0
b101 +
1%
#11600
0%
#11700
b110 +
b1001 0
1%
#11800
0%
#11900
b1010 0
b111 +
1%
#12000
0%
1$
#12100
b1000 +
b1011 0
11
1%
#12200
0%
#12300
1(
12
b1100 0
b1001 +
1%
#12400
0%
#12500
0(
b1010 +
b1101 0
13
1%
#12600
0%
#12700
b1110 0
b1011 +
1%
#12800
0%
#12900
b1100 +
b1111 0
1%
#13000
0%
#13100
b10000 0
b1101 +
1%
#13200
0%
#13300
b1110 +
b10001 0
1%
#13400
0%
#13500
b10010 0
b1111 +
1%
#13600
0%
#13700
b10000 +
b10011 0
1%
#13800
0%
#13900
b10100 0
b10001 +
1%
#14000
0%
#14100
b10010 +
b10101 0
1%
#14200
0%
#14300
b10110 0
b10011 +
1%
#14400
0%
#14500
b10100 +
b10111 0
1%
#14600
0%
#14700
b11000 0
b10101 +
1%
#14800
0%
#14900
b10110 +
b11001 0
1%
#15000
0%
#15100
b11010 0
b10111 +
1%
#15200
0%
#15300
b11000 +
b11011 0
1%
#15400
0%
#15500
b11100 0
b0 +
b1 ,
0.
1%
#15600
0%
#15700
b11101 0
1%
#15800
0%
#15900
b11110 0
1%
#16000
0%
#16100
b11111 0
1%
#16200
0%
#16300
b100000 0
1%
#16400
0%
#16500
b100001 0
1%
#16600
0%
#16700
b100010 0
1%
#16800
0%
#16900
b100011 0
1%
#17000
0%
#17100
b100100 0
1%
#17200
0%
#17300
b100101 0
1%
#17400
0%
#17500
b100110 0
1%
#17600
0%
#17700
b100111 0
1%
#17800
0%
#17900
b101000 0
1%
#18000
0%
#18100
b101001 0
1%
#18200
0%
#18300
b101010 0
1%
#18400
0%
#18500
b101011 0
1%
#18600
0%
#18700
b101100 0
1%
#18800
0%
#18900
b101101 0
1%
#19000
0%
#19100
b101110 0
1%
#19200
0%
#19300
b101111 0
1%
#19400
0%
#19500
b110000 0
1%
#19600
0%
#19700
b110001 0
1%
#19800
0%
#19900
b110010 0
1%
#20000
0%
#20100
b110011 0
1%
#20200
0%
#20300
b110100 0
1%
#20400
0%
#20500
b110101 0
1%
#20600
0%
#20700
b110110 0
1%
#20800
0%
#20900
b110111 0
1%
#21000
0%
#21100
b111000 0
1%
#21200
0%
#21300
b111001 0
1%
#21400
0%
#21500
b111010 0
1%
#21600
0%
#21700
b111011 0
1%
#21800
0%
#21900
b111100 0
1%
#22000
0%
0$
#22100
b111101 0
01
1%
#22200
0%
#22300
1'
02
b111110 0
1%
#22400
0%
#22500
0'
b111111 0
03
1%
#22600
0%
#22700
b1000000 0
1%
#22800
0%
#22900
b1000001 0
1%
#23000
0%
1$
#23100
11
b1000010 0
1%
#23200
0%
#23300
1(
b1000011 0
12
1%
#23400
0%
#23500
0(
13
b1000100 0
1.
1%
#23600
0%
#23700
b1 +
b1000101 0
1%
#23800
0%
#23900
b1000110 0
b10 +
1%
#24000
0%
#24100
b11 +
b1000111 0
1%
#24200
0%
#24300
b1001000 0
b100 +
1%
#24400
0%
#24500
b101 +
b1001001 0
1%
#24600
0%
#24700
b1001010 0
b110 +
1%
#24800
0%
#24900
b111 +
b1001011 0
1%
#25000
0%
#25100
b1001100 0
b1000 +
1%
#25200
0%
#25300
b1001 +
b1001101 0
1%
#25400
0%
#25500
b1001110 0
b1010 +
1%
#25600
0%
#25700
b1011 +
b1001111 0
1%
#25800
0%
#25900
b1010000 0
b1100 +
1%
#26000
0%
#26100
b1101 +
b1010001 0
1%
#26200
0%
#26300
b1010010 0
b1110 +
1%
#26400
0%
#26500
b1111 +
b1010011 0
1%
#26600
0%
#26700
b1010100 0
b10000 +
1%
#26800
0%
#26900
b10001 +
b1010101 0
1%
#27000
0%
#27100
b1010110 0
b10010 +
1%
#27200
0%
#27300
b10011 +
b1010111 0
1%
#27400
0%
#27500
b1011000 0
b10100 +
1%
#27600
0%
#27700
b10101 +
b1011001 0
1%
#27800
0%
#27900
b1011010 0
b10110 +
1%
#28000
0%
#28100
b10111 +
b1011011 0
1%
#28200
0%
#28300
b1011100 0
b11000 +
1%
#28400
0%
#28500
0.
b0 +
b10 ,
b1011101 0
1%
#28600
0%
#28700
b1011110 0
1%
#28800
0%
#28900
b1011111 0
1%
#29000
0%
#29100
b1100000 0
1%
#29200
0%
#29300
b1100001 0
1%
#29400
0%
#29500
b1100010 0
1%
#29600
0%
#29700
b1100011 0
1%
#29800
0%
#29900
b1100100 0
1%
#30000
0%
#30100
b1100101 0
1%
#30200
0%
#30300
b1100110 0
1%
#30400
0%
#30500
b1100111 0
1%
#30600
0%
#30700
b1101000 0
1%
#30800
0%
#30900
b1101001 0
1%
#31000
0%
#31100
b1101010 0
1%
#31200
0%
#31300
b1101011 0
1%
#31400
0%
#31500
b1101100 0
1%
#31600
0%
#31700
b1101101 0
1%
#31800
0%
#31900
b1101110 0
1%
#32000
0%
#32100
b1101111 0
1%
#32200
0%
#32300
b1110000 0
1%
#32400
0%
#32500
b1110001 0
1%
#32600
0%
#32700
b1110010 0
1%
#32800
0%
#32900
b1110011 0
1%
#33000
0%
0$
#33100
01
b1110100 0
1%
#33200
0%
#33300
1'
b1110101 0
02
1%
#33400
0%
#33500
0'
03
b1110110 0
1%
#33600
0%
#33700
b1110111 0
1%
#33800
0%
#33900
b1111000 0
1%
#34000
0%
1$
#34100
b1111001 0
11
1%
#34200
0%
#34300
1(
12
b1111010 0
1%
#34400
0%
#34500
0(
1.
b1111011 0
13
1%
#34600
0%
#34700
b1111100 0
b1 +
1%
#34800
0%
#34900
b10 +
b1111101 0
1%
#35000
0%
#35100
b1111110 0
b11 +
1%
#35200
0%
#35300
b100 +
b1111111 0
1%
#35400
0%
#35500
b10000000 0
b101 +
1%
#35600
0%
#35700
b110 +
b10000001 0
1%
#35800
0%
#35900
b10000010 0
b111 +
1%
#36000
0%
#36100
b1000 +
b10000011 0
1%
#36200
0%
#36300
b10000100 0
b1001 +
1%
#36400
0%
#36500
b1010 +
b10000101 0
1%
#36600
0%
#36700
b10000110 0
b1011 +
1%
#36800
0%
#36900
b1100 +
b10000111 0
1%
#37000
0%
#37100
b10001000 0
b1101 +
1%
#37200
0%
#37300
b1110 +
b10001001 0
1%
#37400
0%
#37500
b10001010 0
b1111 +
1%
#37600
0%
#37700
b10000 +
b10001011 0
1%
#37800
0%
#37900
b10001100 0
b10001 +
1%
#38000
0%
#38100
b10010 +
b10001101 0
1%
#38200
0%
#38300
b10001110 0
b10011 +
1%
#38400
0%
#38500
b10100 +
b10001111 0
1%
#38600
0%
#38700
b10010000 0
b10101 +
1%
#38800
0%
#38900
b10110 +
b10010001 0
1%
#39000
0%
#39100
b10010010 0
b10111 +
1%
#39200
0%
#39300
b11000 +
b10010011 0
1%
#39400
0%
#39500
b10010100 0
b0 +
b11 ,
0.
1%
#39600
0%
#39700
b10010101 0
1%
#39800
0%
#39900
b10010110 0
1%
#40000
0%
#40100
b10010111 0
1%
#40200
0%
#40300
b10011000 0
1%
#40400
0%
#40500
b10011001 0
1%
#40600
0%
#40700
b10011010 0
1%
#40800
0%
#40900
b10011011 0
1%
#41000
0%
#41100
b10011100 0
1%
#41200
0%
#41300
b10011101 0
1%
#41400
0%
#41500
b10011110 0
1%
#41600
0%
#41700
b10011111 0
1%
#41800
0%
#41900
b10100000 0
1%
#42000
0%
#42100
b10100001 0
1%
#42200
0%
#42300
b10100010 0
1%
#42400
0%
#42500
b10100011 0
1%
#42600
0%
#42700
b10100100 0
1%
#42800
0%
#42900
b10100101 0
1%
#43000
0%
#43100
b10100110 0
1%
#43200
0%
#43300
b10100111 0
1%
#43400
0%
#43500
b10101000 0
1%
#43600
0%
#43700
b10101001 0
1%
#43800
0%
#43900
b10101010 0
1%
#44000
0%
0$
#44100
b10101011 0
01
1%
#44200
0%
#44300
1'
02
b10101100 0
1%
#44400
0%
#44500
0'
b10101101 0
03
1%
#44600
0%
#44700
b10101110 0
1%
#44800
0%
#44900
b10101111 0
1%
#45000
0%
1$
#45100
11
b10110000 0
1%
#45200
0%
#45300
1(
b10110001 0
12
1%
#45400
0%
#45500
0(
13
b10110010 0
1.
1%
#45600
0%
#45700
b1 +
b10110011 0
1%
#45800
0%
#45900
b10110100 0
b10 +
1%
#46000
0%
#46100
b11 +
b10110101 0
1%
#46200
0%
#46300
b10110110 0
b100 +
1%
#46400
0%
#46500
b101 +
b10110111 0
1%
#46600
0%
#46700
b10111000 0
b110 +
1%
#46800
0%
#46900
b111 +
b10111001 0
1%
#47000
0%
#47100
b10111010 0
b1000 +
1%
#47200
0%
#47300
b1001 +
b10111011 0
1%
#47400
0%
#47500
b10111100 0
b1010 +
1%
#47600
0%
#47700
b1011 +
b10111101 0
1%
#47800
0%
#47900
b10111110 0
b1100 +
1%
#48000
0%
#48100
b1101 +
b10111111 0
1%
#48200
0%
#48300
b11000000 0
b1110 +
1%
#48400
0%
#48500
b1111 +
b11000001 0
1%
#48600
0%
#48700
b11000010 0
b10000 +
1%
#48800
0%
#48900
b10001 +
b11000011 0
1%
#49000
0%
#49100
b11000100 0
b10010 +
1%
#49200
0%
#49300
b10011 +
b11000101 0
1%
#49400
0%
#49500
b11000110 0
b10100 +
1%
#49600
0%
#49700
b10101 +
b11000111 0
1%
#49800
0%
#49900
b11001000 0
b10110 +
1%
#50000
0%
#50100
b10111 +
b11001001 0
1%
#50200
0%
#50300
b11001010 0
b11000 +
1%
#50400
0%
#50500
0.
b0 +
b100 ,
b11001011 0
1%
#50600
0%
#50700
b11001100 0
1%
#50800
0%
#50900
b11001101 0
1%
#51000
0%
#51100
b11001110 0
1%
#51200
0%
#51300
b11001111 0
1%
#51400
0%
#51500
b11010000 0
1%
#51600
0%
#51700
b11010001 0
1%
#51800
0%
#51900
b11010010 0
1%
#52000
0%
#52100
b11010011 0
1%
#52200
0%
#52300
b11010100 0
1%
#52400
0%
#52500
b11010101 0
1%
#52600
0%
#52700
b11010110 0
1%
#52800
0%
#52900
b11010111 0
1%
#53000
0%
#53100
b11011000 0
1%
#53200
0%
#53300
b11011001 0
1%
#53400
0%
#53500
b11011010 0
1%
#53600
0%
#53700
b11011011 0
1%
#53800
0%
#53900
b11011100 0
1%
#54000
0%
#54100
b11011101 0
1%
#54200
0%
#54300
b11011110 0
1%
#54400
0%
#54500
b11011111 0
1%
#54600
0%
#54700
b11100000 0
1%
#54800
0%
#54900
b11100001 0
1%
#55000
0%
0$
#55100
01
b11100010 0
1%
#55200
0%
#55300
1'
b11100011 0
02
1%
#55400
0%
#55500
0'
03
b11100100 0
1%
#55600
0%
#55700
b11100101 0
1%
#55800
0%
#55900
b11100110 0
1%
#56000
0%
1$
#56100
b11100111 0
11
1%
#56200
0%
#56300
1(
12
b11101000 0
1%
#56400
0%
#56500
0(
1.
b11101001 0
13
1%
#56600
0%
#56700
b11101010 0
b1 +
1%
#56800
0%
#56900
b10 +
b11101011 0
1%
#57000
0%
#57100
b11101100 0
b11 +
1%
#57200
0%
#57300
b100 +
b11101101 0
1%
#57400
0%
#57500
b11101110 0
b101 +
1%
#57600
0%
#57700
b110 +
b11101111 0
1%
#57800
0%
#57900
b11110000 0
b111 +
1%
#58000
0%
#58100
b1000 +
b11110001 0
1%
#58200
0%
#58300
b11110010 0
b1001 +
1%
#58400
0%
#58500
b1010 +
b11110011 0
1%
#58600
0%
#58700
b11110100 0
b1011 +
1%
#58800
0%
#58900
b1100 +
b11110101 0
1%
#59000
0%
#59100
b11110110 0
b1101 +
1%
#59200
0%
#59300
b1110 +
b11110111 0
1%
#59400
0%
#59500
b11111000 0
b1111 +
1%
#59600
0%
#59700
b10000 +
b11111001 0
1%
#59800
0%
#59900
b11111010 0
b10001 +
1%
#60000
0%
#60100
b10010 +
b11111011 0
1%
#60200
0%
#60300
b11111100 0
b10011 +
1%
#60400
0%
#60500
b10100 +
b11111101 0
1%
#60600
0%
#60700
b11111110 0
b10101 +
1%
#60800
0%
#60900
b10110 +
b11111111 0
1%
#61000
0%
#61100
b100000000 0
b10111 +
1%
#61200
0%
#61300
b11000 +
b100000001 0
1%
#61400
0%
#61500
b100000010 0
b0 +
b101 ,
0.
1%
#61600
0%
#61700
b100000011 0
1%
#61800
0%
#61900
b100000100 0
1%
#62000
0%
#62100
b100000101 0
1%
#62200
0%
#62300
b100000110 0
1%
#62400
0%
#62500
b100000111 0
1%
#62600
0%
#62700
b100001000 0
1%
#62800
0%
#62900
b100001001 0
1%
#63000
0%
#63100
b100001010 0
1%
#63200
0%
#63300
b100001011 0
1%
#63400
0%
#63500
b100001100 0
1%
#63600
0%
#63700
b100001101 0
1%
#63800
0%
#63900
b100001110 0
1%
#64000
0%
#64100
b100001111 0
1%
#64200
0%
#64300
b100010000 0
1%
#64400
0%
#64500
b100010001 0
1%
#64600
0%
#64700
b100010010 0
1%
#64800
0%
#64900
b100010011 0
1%
#65000
0%
#65100
b100010100 0
1%
#65200
0%
#65300
b100010101 0
1%
#65400
0%
#65500
b100010110 0
1%
#65600
0%
#65700
b100010111 0
1%
#65800
0%
#65900
b100011000 0
1%
#66000
0%
0$
#66100
b100011001 0
01
1%
#66200
0%
#66300
1'
02
b100011010 0
1%
#66400
0%
#66500
0'
b100011011 0
03
1%
#66600
0%
#66700
b100011100 0
1%
#66800
0%
#66900
b100011101 0
1%
#67000
0%
1$
#67100
11
b100011110 0
1%
#67200
0%
#67300
1(
b100011111 0
12
1%
#67400
0%
#67500
0(
13
b100100000 0
1.
1%
#67600
0%
#67700
b1 +
b100100001 0
1%
#67800
0%
#67900
b100100010 0
b10 +
1%
#68000
0%
#68100
b11 +
b100100011 0
1%
#68200
0%
#68300
b100100100 0
b100 +
1%
#68400
0%
#68500
b101 +
b100100101 0
1%
#68600
0%
#68700
b100100110 0
b110 +
1%
#68800
0%
#68900
b111 +
b100100111 0
1%
#69000
0%
#69100
b100101000 0
b1000 +
1%
#69200
0%
#69300
b1001 +
b100101001 0
1%
#69400
0%
#69500
b100101010 0
b1010 +
1%
#69600
0%
#69700
b1011 +
b100101011 0
1%
#69800
0%
#69900
b100101100 0
b1100 +
1%
#70000
0%
#70100
b1101 +
b100101101 0
1%
#70200
0%
#70300
b100101110 0
b1110 +
1%
#70400
0%
#70500
b1111 +
b100101111 0
1%
#70600
0%
#70700
b100110000 0
b10000 +
1%
#70800
0%
#70900
b10001 +
b100110001 0
1%
#71000
0%
#71100
b100110010 0
b10010 +
1%
#71200
0%
#71300
b10011 +
b100110011 0
1%
#71400
0%
#71500
b100110100 0
b10100 +
1%
#71600
0%
#71700
b10101 +
b100110101 0
1%
#71800
0%
#71900
b100110110 0
b10110 +
1%
#72000
0%
#72100
b10111 +
b100110111 0
1%
#72200
0%
#72300
b100111000 0
b11000 +
1%
#72400
0%
#72500
0.
b0 +
b110 ,
b100111001 0
1%
#72600
0%
#72700
b100111010 0
1%
#72800
0%
#72900
b100111011 0
1%
#73000
0%
#73100
b100111100 0
1%
#73200
0%
#73300
b100111101 0
1%
#73400
0%
#73500
b100111110 0
1%
#73600
0%
#73700
b100111111 0
1%
#73800
0%
#73900
b101000000 0
1%
#74000
0%
#74100
b101000001 0
1%
#74200
0%
#74300
b101000010 0
1%
#74400
0%
#74500
b101000011 0
1%
#74600
0%
#74700
b101000100 0
1%
#74800
0%
#74900
b101000101 0
1%
#75000
0%
#75100
b101000110 0
1%
#75200
0%
#75300
b101000111 0
1%
#75400
0%
#75500
b101001000 0
1%
#75600
0%
#75700
b101001001 0
1%
#75800
0%
#75900
b101001010 0
1%
#76000
0%
#76100
b101001011 0
1%
#76200
0%
#76300
b101001100 0
1%
#76400
0%
#76500
b101001101 0
1%
#76600
0%
#76700
b101001110 0
1%
#76800
0%
#76900
b101001111 0
1%
#77000
0%
0$
#77100
01
b101010000 0
1%
#77200
0%
#77300
1'
b101010001 0
02
1%
#77400
0%
#77500
0'
03
b101010010 0
1%
#77600
0%
#77700
b101010011 0
1%
#77800
0%
#77900
b101010100 0
1%
#78000
0%
1$
#78100
b101010101 0
11
1%
#78200
0%
#78300
1(
12
b101010110 0
1%
#78400
0%
#78500
0(
1.
b101010111 0
13
1%
#78600
0%
#78700
b101011000 0
b1 +
1%
#78800
0%
#78900
b10 +
b101011001 0
1%
#79000
0%
#79100
b101011010 0
b11 +
1%
#79200
0%
#79300
b100 +
b101011011 0
1%
#79400
0%
#79500
b101011100 0
b101 +
1%
#79600
0%
#79700
b110 +
b101011101 0
1%
#79800
0%
#79900
b101011110 0
b111 +
1%
#80000
0%
#80100
b1000 +
b101011111 0
1%
#80200
0%
#80300
b101100000 0
b1001 +
1%
#80400
0%
#80500
b1010 +
b101100001 0
1%
#80600
0%
#80700
b101100010 0
b1011 +
1%
#80800
0%
#80900
b1100 +
b101100011 0
1%
#81000
0%
#81100
b101100100 0
b1101 +
1%
#81200
0%
#81300
b1110 +
b101100101 0
1%
#81400
0%
#81500
b101100110 0
b1111 +
1%
#81600
0%
#81700
b10000 +
b101100111 0
1%
#81800
0%
#81900
b101101000 0
b10001 +
1%
#82000
0%
#82100
b10010 +
b101101001 0
1%
#82200
0%
#82300
b101101010 0
b10011 +
1%
#82400
0%
#82500
b10100 +
b101101011 0
1%
#82600
0%
#82700
b101101100 0
b10101 +
1%
#82800
0%
#82900
b10110 +
b101101101 0
1%
#83000
0%
#83100
b101101110 0
b10111 +
1%
#83200
0%
#83300
b11000 +
b101101111 0
1%
#83400
0%
#83500
b101110000 0
b0 +
b111 ,
0.
1%
#83600
0%
#83700
b101110001 0
1%
#83800
0%
#83900
b101110010 0
1%
#84000
0%
#84100
b101110011 0
1%
#84200
0%
#84300
b101110100 0
1%
#84400
0%
#84500
b101110101 0
1%
#84600
0%
#84700
b101110110 0
1%
#84800
0%
#84900
b101110111 0
1%
#85000
0%
#85100
b101111000 0
1%
#85200
0%
#85300
b101111001 0
1%
#85400
0%
#85500
b101111010 0
1%
#85600
0%
#85700
b101111011 0
1%
#85800
0%
#85900
b101111100 0
1%
#86000
0%
#86100
b101111101 0
1%
#86200
0%
#86300
b101111110 0
1%
#86400
0%
#86500
b101111111 0
1%
#86600
0%
#86700
b110000000 0
1%
#86800
0%
#86900
b110000001 0
1%
#87000
0%
#87100
b110000010 0
1%
#87200
0%
#87300
b110000011 0
1%
#87400
0%
#87500
b110000100 0
1%
#87600
0%
#87700
b110000101 0
1%
#87800
0%
#87900
b110000110 0
1%
#88000
0%
0$
#88100
b110000111 0
01
1%
#88200
0%
#88300
1'
02
b110001000 0
1%
#88400
0%
#88500
0'
b110001001 0
03
1%
#88600
0%
#88700
b110001010 0
1%
#88800
0%
#88900
b110001011 0
1%
#89000
0%
1$
#89100
11
b110001100 0
1%
#89200
0%
#89300
1(
b110001101 0
12
1%
#89400
0%
#89500
0(
13
b110001110 0
1.
1%
#89600
0%
#89700
b1 +
b110001111 0
1%
#89800
0%
#89900
b110010000 0
b10 +
1%
#90000
0%
#90100
b11 +
b110010001 0
1%
#90200
0%
#90300
b110010010 0
b100 +
1%
#90400
0%
#90500
b101 +
b110010011 0
1%
#90600
0%
#90700
b110010100 0
b110 +
1%
#90800
0%
#90900
b111 +
b110010101 0
1%
#91000
0%
#91100
b110010110 0
b1000 +
1%
#91200
0%
#91300
b1001 +
b110010111 0
1%
#91400
0%
#91500
b110011000 0
b1010 +
1%
#91600
0%
#91700
b1011 +
b110011001 0
1%
#91800
0%
#91900
b110011010 0
b1100 +
1%
#92000
0%
#92100
b1101 +
b110011011 0
1%
#92200
0%
#92300
b110011100 0
b1110 +
1%
#92400
0%
#92500
b1111 +
b110011101 0
1%
#92600
0%
#92700
b110011110 0
b10000 +
1%
#92800
0%
#92900
b10001 +
b110011111 0
1%
#93000
0%
#93100
b110100000 0
b10010 +
1%
#93200
0%
#93300
b10011 +
b110100001 0
1%
#93400
0%
#93500
b110100010 0
b10100 +
1%
#93600
0%
#93700
b10101 +
b110100011 0
1%
#93800
0%
#93900
b110100100 0
b10110 +
1%
#94000
0%
#94100
b10111 +
b110100101 0
1%
#94200
0%
#94300
b110100110 0
b11000 +
1%
#94400
0%
#94500
0.
b0 +
b1000 ,
b110100111 0
1%
#94600
0%
#94700
b110101000 0
1%
#94800
0%
#94900
b110101001 0
1%
#95000
0%
#95100
b110101010 0
1%
#95200
0%
#95300
b110101011 0
1%
#95400
0%
#95500
b110101100 0
1%
#95600
0%
#95700
b110101101 0
1%
#95800
0%
#95900
b110101110 0
1%
#96000
0%
#96100
b110101111 0
1%
#96200
0%
#96300
b110110000 0
1%
#96400
0%
#96500
b110110001 0
1%
#96600
0%
#96700
b110110010 0
1%
#96800
0%
#96900
b110110011 0
1%
#97000
0%
#97100
b110110100 0
1%
#97200
0%
#97300
b110110101 0
1%
#97400
0%
#97500
b110110110 0
1%
#97600
0%
#97700
b110110111 0
1%
#97800
0%
#97900
b110111000 0
1%
#98000
0%
#98100
b110111001 0
1%
#98200
0%
#98300
b110111010 0
1%
#98400
0%
#98500
b110111011 0
1%
#98600
0%
#98700
b110111100 0
1%
#98800
0%
#98900
b110111101 0
1%
#99000
0%
0$
#99100
01
b110111110 0
1%
#99200
0%
#99300
1'
b110111111 0
02
1%
#99400
0%
#99500
0'
03
b111000000 0
1%
#99600
0%
#99700
b111000001 0
1%
#99800
0%
#99900
b111000010 0
1%
#100000
0%
1$
#100100
b111000011 0
11
1%
#100200
0%
#100300
1(
12
b111000100 0
1%
#100400
0%
#100500
0(
1.
b111000101 0
13
1%
#100600
0%
#100700
b111000110 0
b1 +
1%
#100800
0%
#100900
b10 +
b111000111 0
1%
#101000
0%
#101100
b111001000 0
b11 +
1%
#101200
0%
#101300
b100 +
b111001001 0
1%
#101400
0%
#101500
b111001010 0
b101 +
1%
#101600
0%
#101700
b110 +
b111001011 0
1%
#101800
0%
#101900
b111001100 0
b111 +
1%
#102000
0%
#102100
b1000 +
b111001101 0
1%
#102200
0%
#102300
b111001110 0
b1001 +
1%
#102400
0%
#102500
b1010 +
b111001111 0
1%
#102600
0%
#102700
b111010000 0
b1011 +
1%
#102800
0%
#102900
b1100 +
b111010001 0
1%
#103000
0%
#103100
b111010010 0
b1101 +
1%
#103200
0%
#103300
b1110 +
b111010011 0
1%
#103400
0%
#103500
b111010100 0
b1111 +
1%
#103600
0%
#103700
b10000 +
b111010101 0
1%
#103800
0%
#103900
b111010110 0
b10001 +
1%
#104000
0%
#104100
b10010 +
b111010111 0
1%
#104200
0%
#104300
b111011000 0
b10011 +
1%
#104400
0%
#104500
b10100 +
b111011001 0
1%
#104600
0%
#104700
b111011010 0
b10101 +
1%
