week6/task1_3.v
`define CNT_MAX 32'd25
module task1_3(
    input clk,
    input reset,
    input button_io1,
    input button_io2,
    input button_io3,
    output reg clk_div,
    output reg [7:0] led_io
);

reg pulse1_1, pulse1_2, pulse1_3;
always @(posedge clk or posedge reset) begin
    //这里实现了按键1的下降沿检测
    if(reset)
    begin 
        pulse1_1 <= 1'b0;
        pulse1_2 <= 1'b0;
        pulse1_3 <= 1'b0;
    end
    else
    begin
        pulse1_1 <= button_io1;
        pulse1_2 <= pulse1_1;
        pulse1_3 <= pulse1_2;
    end
end
wire button1_negedge = ~pulse1_2 & pulse1_3;
wire button1_posedge = pulse1_2 & ~pulse1_3;

reg pulse2_1, pulse2_2, pulse2_3;
always @(posedge clk or posedge reset) begin
    //这里实现了按键2的下降沿检测
    if(reset)
    begin 
        pulse2_1 <= 1'b0;
        pulse2_2 <= 1'b0;
        pulse2_3 <= 1'b0;
    end
    else
    begin
        pulse2_1 <= button_io2;
        pulse2_2 <= pulse2_1;
        pulse2_3 <= pulse2_2;
    end
end
wire button2_negedge = ~pulse2_2 & pulse2_3;
wire button2_posedge = pulse2_2 & ~pulse2_3;

reg pulse3_1, pulse3_2, pulse3_3;
always @(posedge clk or posedge reset) begin
    //这里实现了按键3的下降沿检测，我知道这很蠢，但是我不想改
    if(reset)
    begin 
        pulse3_1 <= 1'b0;
        pulse3_2 <= 1'b0;
        pulse3_3 <= 1'b0;
    end
    else
    begin
        pulse3_1 <= button_io3;
        pulse3_2 <= pulse3_1;
        pulse3_3 <= pulse3_2;
    end
end
wire button3_negedge = ~pulse3_2 & pulse3_3;
wire button3_posedge = pulse3_2 & ~pulse3_3;

reg [31:0] div_reg;
always @ (posedge clk or posedge reset)
    //这里实现了一个1s的计数器
    if(reset)
    begin
        div_reg <= 32'b0;
        clk_div <= 1'b0;
    end

    else
    begin
        if(div_reg < 32'd12500000)
            div_reg <= div_reg + 32'b1;
        else
        begin
            div_reg <= 32'b0;
            clk_div <= ~clk_div;
        end
    end

reg [31:0] cnt;
always @ (posedge clk or posedge reset)begin
    //这里实现了按键的延时
    if(reset) begin
        cnt <= 32'b0;
    end
    else if(delay_flag) begin
        if(cnt == `CNT_MAX-1)
            cnt <= 32'b0;
        else begin
            cnt <= cnt + 32'b1;
        end
    end
end


reg delay_flag; //还挺好奇三个按键是否得用三个flag
always @(posedge clk or posedge reset) begin
    if(reset) begin
        delay_flag <= 1'b0;
    end
    else if(button1_posedge || button2_posedge || button3_posedge) begin
        delay_flag <= 1'b1;
    end
    else if(cnt == `CNT_MAX-1) begin
        delay_flag <= 1'b0;
    end
end

reg button1_state, button2_state, button3_state;
always @(posedge clk or posedge reset) begin
    if(reset) begin
        button1_state <= 1'b0;
        button2_state <= 1'b0;
        button3_state <= 1'b0;
    end
    else if(cnt == `CNT_MAX-1) begin
        button1_state <= button_io1;
        button2_state <= button_io2;
        button3_state <= button_io3;
    end
    else begin
        button1_state <= 1'b0;
        button2_state <= 1'b0;
        button3_state <= 1'b0;
    end
end

reg led_state1_flag, led_state2_flag, led_state3_flag;
always @(posedge clk or posedge reset) begin
    if(reset) begin
        led_state1_flag <= 1'b0;
        led_state2_flag <= 1'b0;
        led_state3_flag <= 1'b0;
    end
    else if(button1_state) begin
        led_state1_flag <= 1'b1;
        led_state2_flag <= 1'b0;
        led_state3_flag <= 1'b0;
    end     
    else if(button2_state) begin
        led_state1_flag <= 1'b0;
        led_state2_flag <= 1'b1;
        led_state3_flag <= 1'b0;
    end
    else if(stop_flag) begin
        led_state1_flag <= 1'b0;
        led_state2_flag <= 1'b0;
        led_state3_flag <= 1'b0;
    end
    else if(button3_state) begin
        led_state1_flag <= 1'b0;
        led_state2_flag <= 1'b0;
        led_state3_flag <= 1'b1;
    end

end

reg led_cnt;//led计数器
reg stop_flag;//停止标志位
always @(posedge clk_div or posedge reset) begin
    if(reset) begin
        led_io <= 8'b0;
        led_cnt <= 8'b0;
        stop_flag <= 1'b0;
    end
    else if(led_state1_flag) begin
        if(led_io == 8'b10000000 || led_io == 8'b00000000) begin
            led_io <= 8'b00000001;
        end
        else begin
            led_io <= led_io << 1;
        end
    end

    else if(led_state2_flag) begin
        if(led_io == 8'b00000001 || led_io == 8'b00000000) begin
            led_io <= 8'b10000000;
        end
        else begin
            led_io <= led_io >> 1;
        end
    end
    else if(led_state3_flag) begin
        if(led_io != 8'b0) begin
            led_io <= 8'b0;
        end
        else begin
            led_io <= 8'b11111111;
            led_cnt <= led_cnt + 1;
        end
    end

    if(led_cnt == 8'd2 ) begin//这个地方是8'd1为啥过不了？
        stop_flag <= 1'b1;
    end
    else if(led_cnt == 8'd3) begin
        led_cnt <= 0;
    end
    else begin
        stop_flag <= 1'b0;
    end
end

endmodule

week6/tb_task1_3.v
//~ `New testbench
`timescale 1ns / 1ps
`include "task1_3.v"
module tb_task1_3;

    // task1_3 Parameters
    parameter PERIOD = 10;

    // task1_3 Inputs
    reg clk = 0;
    reg reset = 0;
    reg button_io1 = 0;
    reg button_io2 = 0;
    reg button_io3 = 0;


    // task1_3 Outputs
    wire clk_div;
    wire [7:0] led_io;
    
    task1_3 u_task1_3 (
        .clk        (clk),
        .reset      (reset),
        .button_io1 (button_io1),
        .button_io2 (button_io2),
        .button_io3 (button_io3),
        .clk_div    (clk_div),
        .led_io     (led_io[7:0])
    );

    initial begin
        $dumpfile("./wave/tb_task1_3.vcd");
        $dumpvars(0, tb_task1_3);
        clk = 0;
        reset = 1;
        #10
        reset = 0;
        #10000
        $finish;
    end

    always begin
      #0.1 clk = ~clk;
    end

    always begin
        button_io1 = 1;
        #10 button_io1 = 0;
        #1 button_io1 = 0;
        button_io2 = 1;
        #10 button_io2 = 0;
        #1 button_io2 = 0;
        button_io3 = 1;
        #10 button_io3 = 0;
        #1 button_io3 = 0;
    end

endmodule

week6/wave/tb_task1_3.vcd
$date
	Fri Nov 10 10:52:10 2023
$end
$version
	Icarus Verilog
$end
$timescale
	1ps
$end
$scope module tb_task1_3 $end
$var wire 8 ! led_io [7:0] $end
$var wire 1 " clk_div $end
$var parameter 32 # PERIOD $end
$var reg 1 $ button_io1 $end
$var reg 1 % button_io2 $end
$var reg 1 & button_io3 $end
$var reg 1 ' clk $end
$var reg 1 ( reset $end
$scope module u_task1_3 $end
$var wire 1 ) button1_negedge $end
$var wire 1 * button1_posedge $end
$var wire 1 + button2_negedge $end
$var wire 1 , button2_posedge $end
$var wire 1 - button3_negedge $end
$var wire 1 . button3_posedge $end
$var wire 1 $ button_io1 $end
$var wire 1 % button_io2 $end
$var wire 1 & button_io3 $end
$var wire 1 ' clk $end
$var wire 1 ( reset $end
$var reg 1 / button1_state $end
$var reg 1 0 button2_state $end
$var reg 1 1 button3_state $end
$var reg 1 " clk_div $end
$var reg 32 2 cnt [31:0] $end
$var reg 1 3 delay_flag $end
$var reg 32 4 div_reg [31:0] $end
$var reg 1 5 led_cnt $end
$var reg 8 6 led_io [7:0] $end
$var reg 1 7 led_state1_flag $end
$var reg 1 8 led_state2_flag $end
$var reg 1 9 led_state3_flag $end
$var reg 1 : pulse1_1 $end
$var reg 1 ; pulse1_2 $end
$var reg 1 < pulse1_3 $end
$var reg 1 = pulse2_1 $end
$var reg 1 > pulse2_2 $end
$var reg 1 ? pulse2_3 $end
$var reg 1 @ pulse3_1 $end
$var reg 1 A pulse3_2 $end
$var reg 1 B pulse3_3 $end
$var reg 1 C stop_flag $end
$upscope $end
$upscope $end
$enddefinitions $end
$comment Show the parameter values. $end
$dumpall
b1010 #
$end
#0
$dumpvars
0C
0B
0A
0@
0?
0>
0=
0<
0;
0:
09
08
07
b0 6
05
b0 4
03
b0 2
01
00
0/
0.
0-
0,
0+
0*
0)
1(
0'
0&
0%
1$
0"
b0 !
$end
#100
1'
#200
0'
#300
1'
#400
0'
#500
1'
#600
0'
#700
1'
#800
0'
#900
1'
#1000
0'
#1100
1'
#1200
0'
#1300
1'
#1400
0'
#1500
1'
#1600
0'
#1700
1'
#1800
0'
#1900
1'
#2000
0'
#2100
1'
#2200
0'
#2300
1'
#2400
0'
#2500
1'
#2600
0'
#2700
1'
#2800
0'
#2900
1'
#3000
0'
#3100
1'
#3200
0'
#3300
1'
#3400
0'
#3500
1'
#3600
0'
#3700
1'
#3800
0'
#3900
1'
#4000
0'
#4100
1'
#4200
0'
#4300
1'
#4400
0'
#4500
1'
#4600
0'
#4700
1'
#4800
0'
#4900
1'
#5000
0'
#5100
1'
#5200
0'
#5300
1'
#5400
0'
#5500
1'
#5600
0'
#5700
1'
#5800
0'
#5900
1'
#6000
0'
#6100
1'
#6200
0'
#6300
1'
#6400
0'
#6500
1'
#6600
0'
#6700
1'
#6800
0'
#6900
1'
#7000
0'
#7100
1'
#7200
0'
#7300
1'
#7400
0'
#7500
1'
#7600
0'
#7700
1'
#7800
0'
#7900
1'
#8000
0'
#8100
1'
#8200
0'
#8300
1'
#8400
0'
#8500
1'
#8600
0'
#8700
1'
#8800
0'
#8900
1'
#9000
0'
#9100
1'
#9200
0'
#9300
1'
#9400
0'
#9500
1'
#9600
0'
#9700
1'
#9800
0'
#9900
1'
#10000
0'
0$
0(
#10100
b1 4
1'
#10200
0'
#10300
b10 4
1'
#10400
0'
#10500
b11 4
1'
#10600
0'
#10700
b100 4
1'
#10800
0'
#10900
b101 4
1'
#11000
0'
1%
#11100
1=
b110 4
1'
#11200
0'
#11300
1,
b111 4
1>
1'
#11400
0'
#11500
0,
1?
b1000 4
13
1'
#11600
0'
#11700
b1 2
b1001 4
1'
#11800
0'
#11900
b1010 4
b10 2
1'
#12000
0'
#12100
b11 2
b1011 4
1'
#12200
0'
#12300
b1100 4
b100 2
1'
#12400
0'
#12500
b101 2
b1101 4
1'
#12600
0'
#12700
b1110 4
b110 2
1'
#12800
0'
#12900
b111 2
b1111 4
1'
#13000
0'
#13100
b10000 4
b1000 2
1'
#13200
0'
#13300
b1001 2
b10001 4
1'
#13400
0'
#13500
b10010 4
b1010 2
1'
#13600
0'
#13700
b1011 2
b10011 4
1'
#13800
0'
#13900
b10100 4
b1100 2
1'
#14000
0'
#14100
b1101 2
b10101 4
1'
#14200
0'
#14300
b10110 4
b1110 2
1'
#14400
0'
#14500
b1111 2
b10111 4
1'
#14600
0'
#14700
b11000 4
b10000 2
1'
#14800
0'
#14900
b10001 2
b11001 4
1'
#15000
0'
#15100
b11010 4
b10010 2
1'
#15200
0'
#15300
b10011 2
b11011 4
1'
#15400
0'
#15500
b11100 4
b10100 2
1'
#15600
0'
#15700
b10101 2
b11101 4
1'
#15800
0'
#15900
b11110 4
b10110 2
1'
#16000
0'
#16100
b10111 2
b11111 4
1'
#16200
0'
#16300
b100000 4
b11000 2
1'
#16400
0'
#16500
10
03
b0 2
b100001 4
1'
#16600
0'
#16700
b100010 4
00
18
1'
#16800
0'
#16900
b100011 4
1'
#17000
0'
#17100
b100100 4
1'
#17200
0'
#17300
b100101 4
1'
#17400
0'
#17500
b100110 4
1'
#17600
0'
#17700
b100111 4
1'
#17800
0'
#17900
b101000 4
1'
#18000
0'
#18100
b101001 4
1'
#18200
0'
#18300
b101010 4
1'
#18400
0'
#18500
b101011 4
1'
#18600
0'
#18700
b101100 4
1'
#18800
0'
#18900
b101101 4
1'
#19000
0'
#19100
b101110 4
1'
#19200
0'
#19300
b101111 4
1'
#19400
0'
#19500
b110000 4
1'
#19600
0'
#19700
b110001 4
1'
#19800
0'
#19900
b110010 4
1'
#20000
0'
#20100
b110011 4
1'
#20200
0'
#20300
b110100 4
1'
#20400
0'
#20500
b110101 4
1'
#20600
0'
#20700
b110110 4
1'
#20800
0'
#20900
b110111 4
1'
#21000
0'
0%
#21100
0=
b111000 4
1'
#21200
0'
#21300
1+
b111001 4
0>
1'
#21400
0'
#21500
0+
0?
b111010 4
1'
#21600
0'
#21700
b111011 4
1'
#21800
0'
#21900
b111100 4
1'
#22000
0'
1&
#22100
b111101 4
1@
1'
#22200
0'
#22300
1.
1A
b111110 4
1'
#22400
0'
#22500
0.
13
b111111 4
1B
1'
#22600
0'
#22700
b1000000 4
b1 2
1'
#22800
0'
#22900
b10 2
b1000001 4
1'
#23000
0'
#23100
b1000010 4
b11 2
1'
#23200
0'
#23300
b100 2
b1000011 4
1'
#23400
0'
#23500
b1000100 4
b101 2
1'
#23600
0'
#23700
b110 2
b1000101 4
1'
#23800
0'
#23900
b1000110 4
b111 2
1'
#24000
0'
#24100
b1000 2
b1000111 4
1'
#24200
0'
#24300
b1001000 4
b1001 2
1'
#24400
0'
#24500
b1010 2
b1001001 4
1'
#24600
0'
#24700
b1001010 4
b1011 2
1'
#24800
0'
#24900
b1100 2
b1001011 4
1'
#25000
0'
#25100
b1001100 4
b1101 2
1'
#25200
0'
#25300
b1110 2
b1001101 4
1'
#25400
0'
#25500
b1001110 4
b1111 2
1'
#25600
0'
#25700
b10000 2
b1001111 4
1'
#25800
0'
#25900
b1010000 4
b10001 2
1'
#26000
0'
#26100
b10010 2
b1010001 4
1'
#26200
0'
#26300
b1010010 4
b10011 2
1'
#26400
0'
#26500
b10100 2
b1010011 4
1'
#26600
0'
#26700
b1010100 4
b10101 2
1'
#26800
0'
#26900
b10110 2
b1010101 4
1'
#27000
0'
#27100
b1010110 4
b10111 2
1'
#27200
0'
#27300
b11000 2
b1010111 4
1'
#27400
0'
#27500
b1011000 4
b0 2
03
11
1'
#27600
0'
#27700
19
08
01
b1011001 4
1'
#27800
0'
#27900
b1011010 4
1'
#28000
0'
#28100
b1011011 4
1'
#28200
0'
#28300
b1011100 4
1'
#28400
0'
#28500
b1011101 4
1'
#28600
0'
#28700
b1011110 4
1'
#28800
0'
#28900
b1011111 4
1'
#29000
0'
#29100
b1100000 4
1'
#29200
0'
#29300
b1100001 4
1'
#29400
0'
#29500
b1100010 4
1'
#29600
0'
#29700
b1100011 4
1'
#29800
0'
#29900
b1100100 4
1'
#30000
0'
#30100
b1100101 4
1'
#30200
0'
#30300
b1100110 4
1'
#30400
0'
#30500
b1100111 4
1'
#30600
0'
#30700
b1101000 4
1'
#30800
0'
#30900
b1101001 4
1'
#31000
0'
#31100
b1101010 4
1'
#31200
0'
#31300
b1101011 4
1'
#31400
0'
#31500
b1101100 4
1'
#31600
0'
#31700
b1101101 4
1'
#31800
0'
#31900
b1101110 4
1'
#32000
0'
0&
#32100
b1101111 4
0@
1'
#32200
0'
#32300
1-
0A
b1110000 4
1'
#32400
0'
#32500
0-
b1110001 4
0B
1'
#32600
0'
#32700
b1110010 4
1'
#32800
0'
#32900
b1110011 4
1'
#33000
0'
1$
#33100
1:
b1110100 4
1'
#33200
0'
#33300
1*
b1110101 4
1;
1'
#33400
0'
#33500
0*
1<
b1110110 4
13
1'
#33600
0'
#33700
b1 2
b1110111 4
1'
#33800
0'
#33900
b1111000 4
b10 2
1'
#34000
0'
#34100
b11 2
b1111001 4
1'
#34200
0'
#34300
b1111010 4
b100 2
1'
#34400
0'
#34500
b101 2
b1111011 4
1'
#34600
0'
#34700
b1111100 4
b110 2
1'
#34800
0'
#34900
b111 2
b1111101 4
1'
#35000
0'
#35100
b1111110 4
b1000 2
1'
#35200
0'
#35300
b1001 2
b1111111 4
1'
#35400
0'
#35500
b10000000 4
b1010 2
1'
#35600
0'
#35700
b1011 2
b10000001 4
1'
#35800
0'
#35900
b10000010 4
b1100 2
1'
#36000
0'
#36100
b1101 2
b10000011 4
1'
#36200
0'
#36300
b10000100 4
b1110 2
1'
#36400
0'
#36500
b1111 2
b10000101 4
1'
#36600
0'
#36700
b10000110 4
b10000 2
1'
#36800
0'
#36900
b10001 2
b10000111 4
1'
#37000
0'
#37100
b10001000 4
b10010 2
1'
#37200
0'
#37300
b10011 2
b10001001 4
1'
#37400
0'
#37500
b10001010 4
b10100 2
1'
#37600
0'
#37700
b10101 2
b10001011 4
1'
#37800
0'
#37900
b10001100 4
b10110 2
1'
#38000
0'
#38100
b10111 2
b10001101 4
1'
#38200
0'
#38300
b10001110 4
b11000 2
1'
#38400
0'
#38500
1/
03
b0 2
b10001111 4
1'
#38600
0'
#38700
b10010000 4
0/
09
17
1'
#38800
0'
#38900
b10010001 4
1'
#39000
0'
#39100
b10010010 4
1'
#39200
0'
#39300
b10010011 4
1'
#39400
0'
#39500
b10010100 4
1'
#39600
0'
#39700
b10010101 4
1'
#39800
0'
#39900
b10010110 4
1'
#40000
0'
#40100
b10010111 4
1'
#40200
0'
#40300
b10011000 4
1'
#40400
0'
#40500
b10011001 4
1'
#40600
0'
#40700
b10011010 4
1'
#40800
0'
#40900
b10011011 4
1'
#41000
0'
#41100
b10011100 4
1'
#41200
0'
#41300
b10011101 4
1'
#41400
0'
#41500
b10011110 4
1'
#41600
0'
#41700
b10011111 4
1'
#41800
0'
#41900
b10100000 4
1'
#42000
0'
#42100
b10100001 4
1'
#42200
0'
#42300
b10100010 4
1'
#42400
0'
#42500
b10100011 4
1'
#42600
0'
#42700
b10100100 4
1'
#42800
0'
#42900
b10100101 4
1'
#43000
0'
0$
#43100
0:
b10100110 4
1'
#43200
0'
#43300
1)
b10100111 4
0;
1'
#43400
0'
#43500
0)
0<
b10101000 4
1'
#43600
0'
#43700
b10101001 4
1'
#43800
0'
#43900
b10101010 4
1'
#44000
0'
1%
#44100
b10101011 4
1=
1'
#44200
0'
#44300
1,
1>
b10101100 4
1'
#44400
0'
#44500
0,
13
b10101101 4
1?
1'
#44600
0'
#44700
b10101110 4
b1 2
1'
#44800
0'
#44900
b10 2
b10101111 4
1'
#45000
0'
#45100
b10110000 4
b11 2
1'
#45200
0'
#45300
b100 2
b10110001 4
1'
#45400
0'
#45500
b10110010 4
b101 2
1'
#45600
0'
#45700
b110 2
b10110011 4
1'
#45800
0'
#45900
b10110100 4
b111 2
1'
#46000
0'
#46100
b1000 2
b10110101 4
1'
#46200
0'
#46300
b10110110 4
b1001 2
1'
#46400
0'
#46500
b1010 2
b10110111 4
1'
#46600
0'
#46700
b10111000 4
b1011 2
1'
#46800
0'
#46900
b1100 2
b10111001 4
1'
#47000
0'
#47100
b10111010 4
b1101 2
1'
#47200
0'
#47300
b1110 2
b10111011 4
1'
#47400
0'
#47500
b10111100 4
b1111 2
1'
#47600
0'
#47700
b10000 2
b10111101 4
1'
#47800
0'
#47900
b10111110 4
b10001 2
1'
#48000
0'
#48100
b10010 2
b10111111 4
1'
#48200
0'
#48300
b11000000 4
b10011 2
1'
#48400
0'
#48500
b10100 2
b11000001 4
1'
#48600
0'
#48700
b11000010 4
b10101 2
1'
#48800
0'
#48900
b10110 2
b11000011 4
1'
#49000
0'
#49100
b11000100 4
b10111 2
1'
#49200
0'
#49300
b11000 2
b11000101 4
1'
#49400
0'
#49500
b11000110 4
b0 2
03
10
1'
#49600
0'
#49700
18
07
00
b11000111 4
1'
#49800
0'
#49900
b11001000 4
1'
#50000
0'
#50100
b11001001 4
1'
#50200
0'
#50300
b11001010 4
1'
#50400
0'
#50500
b11001011 4
1'
#50600
0'
#50700
b11001100 4
1'
#50800
0'
#50900
b11001101 4
1'
#51000
0'
#51100
b11001110 4
1'
#51200
0'
#51300
b11001111 4
1'
#51400
0'
#51500
b11010000 4
1'
#51600
0'
#51700
b11010001 4
1'
#51800
0'
#51900
b11010010 4
1'
#52000
0'
#52100
b11010011 4
1'
#52200
0'
#52300
b11010100 4
1'
#52400
0'
#52500
b11010101 4
1'
#52600
0'
#52700
b11010110 4
1'
#52800
0'
#52900
b11010111 4
1'
#53000
0'
#53100
b11011000 4
1'
#53200
0'
#53300
b11011001 4
1'
#53400
0'
#53500
b11011010 4
1'
#53600
0'
#53700
b11011011 4
1'
#53800
0'
#53900
b11011100 4
1'
#54000
0'
0%
#54100
b11011101 4
0=
1'
#54200
0'
#54300
1+
0>
b11011110 4
1'
#54400
0'
#54500
0+
b11011111 4
0?
1'
#54600
0'
#54700
b11100000 4
1'
#54800
0'
#54900
b11100001 4
1'
#55000
0'
1&
#55100
1@
b11100010 4
1'
#55200
0'
#55300
1.
b11100011 4
1A
1'
#55400
0'
#55500
0.
1B
b11100100 4
13
1'
#55600
0'
#55700
b1 2
b11100101 4
1'
#55800
0'
#55900
b11100110 4
b10 2
1'
#56000
0'
#56100
b11 2
b11100111 4
1'
#56200
0'
#56300
b11101000 4
b100 2
1'
#56400
0'
#56500
b101 2
b11101001 4
1'
#56600
0'
#56700
b11101010 4
b110 2
1'
#56800
0'
#56900
b111 2
b11101011 4
1'
#57000
0'
#57100
b11101100 4
b1000 2
1'
#57200
0'
#57300
b1001 2
b11101101 4
1'
#57400
0'
#57500
b11101110 4
b1010 2
1'
#57600
0'
#57700
b1011 2
b11101111 4
1'
#57800
0'
#57900
b11110000 4
b1100 2
1'
#58000
0'
#58100
b1101 2
b11110001 4
1'
#58200
0'
#58300
b11110010 4
b1110 2
1'
#58400
0'
#58500
b1111 2
b11110011 4
1'
#58600
0'
#58700
b11110100 4
b10000 2
1'
#58800
0'
#58900
b10001 2
b11110101 4
1'
#59000
0'
#59100
b11110110 4
b10010 2
1'
#59200
0'
#59300
b10011 2
b11110111 4
1'
#59400
0'
#59500
b11111000 4
b10100 2
1'
#59600
0'
#59700
b10101 2
b11111001 4
1'
#59800
0'
#59900
b11111010 4
b10110 2
1'
#60000
0'
#60100
b10111 2
b11111011 4
1'
#60200
0'
#60300
b11111100 4
b11000 2
1'
#60400
0'
#60500
11
03
b0 2
b11111101 4
1'
#60600
0'
#60700
b11111110 4
01
19
08
1'
#60800
0'
#60900
b11111111 4
1'
#61000
0'
#61100
b100000000 4
1'
#61200
0'
#61300
b100000001 4
1'
#61400
0'
#61500
b100000010 4
1'
#61600
0'
#61700
b100000011 4
1'
#61800
0'
#61900
b100000100 4
1'
#62000
0'
#62100
b100000101 4
1'
#62200
0'
#62300
b100000110 4
1'
#62400
0'
#62500
b100000111 4
1'
#62600
0'
#62700
b100001000 4
1'
#62800
0'
#62900
b100001001 4
1'
#63000
0'
#63100
b100001010 4
1'
#63200
0'
#63300
b100001011 4
1'
#63400
0'
#63500
b100001100 4
1'
#63600
0'
#63700
b100001101 4
1'
#63800
0'
#63900
b100001110 4
1'
#64000
0'
#64100
b100001111 4
1'
#64200
0'
#64300
b100010000 4
1'
#64400
0'
#64500
b100010001 4
1'
#64600
0'
#64700
b100010010 4
1'
#64800
0'
#64900
b100010011 4
1'
#65000
0'
0&
#65100
0@
b100010100 4
1'
#65200
0'
#65300
1-
b100010101 4
0A
1'
#65400
0'
#65500
0-
0B
b100010110 4
1'
#65600
0'
#65700
b100010111 4
1'
#65800
0'
#65900
b100011000 4
1'
#66000
0'
1$
#66100
b100011001 4
1:
1'
#66200
0'
#66300
1*
1;
b100011010 4
1'
#66400
0'
#66500
0*
13
b100011011 4
1<
1'
#66600
0'
#66700
b100011100 4
b1 2
1'
#66800
0'
#66900
b10 2
b100011101 4
1'
#67000
0'
#67100
b100011110 4
b11 2
1'
#67200
0'
#67300
b100 2
b100011111 4
1'
#67400
0'
#67500
b100100000 4
b101 2
1'
#67600
0'
#67700
b110 2
b100100001 4
1'
#67800
0'
#67900
b100100010 4
b111 2
1'
#68000
0'
#68100
b1000 2
b100100011 4
1'
#68200
0'
#68300
b100100100 4
b1001 2
1'
#68400
0'
#68500
b1010 2
b100100101 4
1'
#68600
0'
#68700
b100100110 4
b1011 2
1'
#68800
0'
#68900
b1100 2
b100100111 4
1'
#69000
0'
#69100
b100101000 4
b1101 2
1'
#69200
0'
#69300
b1110 2
b100101001 4
1'
#69400
0'
#69500
b100101010 4
b1111 2
1'
#69600
0'
#69700
b10000 2
b100101011 4
1'
#69800
0'
#69900
b100101100 4
b10001 2
1'
#70000
0'
#70100
b10010 2
b100101101 4
1'
#70200
0'
#70300
b100101110 4
b10011 2
1'
#70400
0'
#70500
b10100 2
b100101111 4
1'
#70600
0'
#70700
b100110000 4
b10101 2
1'
#70800
0'
#70900
b10110 2
b100110001 4
1'
#71000
0'
#71100
b100110010 4
b10111 2
1'
#71200
0'
#71300
b11000 2
b100110011 4
1'
#71400
0'
#71500
b100110100 4
b0 2
03
1/
1'
#71600
0'
#71700
09
17
0/
b100110101 4
1'
#71800
0'
#71900
b100110110 4
1'
#72000
0'
#72100
b100110111 4
1'
#72200
0'
#72300
b100111000 4
1'
#72400
0'
#72500
b100111001 4
1'
#72600
0'
#72700
b100111010 4
1'
#72800
0'
#72900
b100111011 4
1'
#73000
0'
#73100
b100111100 4
1'
#73200
0'
#73300
b100111101 4
1'
#73400
0'
#73500
b100111110 4
1'
#73600
0'
#73700
b100111111 4
1'
#73800
0'
#73900
b101000000 4
1'
#74000
0'
#74100
b101000001 4
1'
#74200
0'
#74300
b101000010 4
1'
#74400
0'
#74500
b101000011 4
1'
#74600
0'
#74700
b101000100 4
1'
#74800
0'
#74900
b101000101 4
1'
#75000
0'
#75100
b101000110 4
1'
#75200
0'
#75300
b101000111 4
1'
#75400
0'
#75500
b101001000 4
1'
#75600
0'
#75700
b101001001 4
1'
#75800
0'
#75900
b101001010 4
1'
#76000
0'
0$
#76100
b101001011 4
0:
1'
#76200
0'
#76300
1)
0;
b101001100 4
1'
#76400
0'
#76500
0)
b101001101 4
0<
1'
#76600
0'
#76700
b101001110 4
1'
#76800
0'
#76900
b101001111 4
1'
#77000
0'
1%
#77100
1=
b101010000 4
1'
#77200
0'
#77300
1,
b101010001 4
1>
1'
#77400
0'
#77500
0,
1?
b101010010 4
13
1'
#77600
0'
#77700
b1 2
b101010011 4
1'
#77800
0'
#77900
b101010100 4
b10 2
1'
#78000
0'
#78100
b11 2
b101010101 4
1'
#78200
0'
#78300
b101010110 4
b100 2
1'
#78400
0'
#78500
b101 2
b101010111 4
1'
#78600
0'
#78700
b101011000 4
b110 2
1'
#78800
0'
#78900
b111 2
b101011001 4
1'
#79000
0'
#79100
b101011010 4
b1000 2
1'
#79200
0'
#79300
b1001 2
b101011011 4
1'
#79400
0'
#79500
b101011100 4
b1010 2
1'
#79600
0'
#79700
b1011 2
b101011101 4
1'
#79800
0'
#79900
b101011110 4
b1100 2
1'
#80000
0'
#80100
b1101 2
b101011111 4
1'
#80200
0'
#80300
b101100000 4
b1110 2
1'
#80400
0'
#80500
b1111 2
b101100001 4
1'
#80600
0'
#80700
b101100010 4
b10000 2
1'
#80800
0'
#80900
b10001 2
b101100011 4
1'
#81000
0'
#81100
b101100100 4
b10010 2
1'
#81200
0'
#81300
b10011 2
b101100101 4
1'
#81400
0'
#81500
b101100110 4
b10100 2
1'
#81600
0'
#81700
b10101 2
b101100111 4
1'
#81800
0'
#81900
b101101000 4
b10110 2
1'
#82000
0'
#82100
b10111 2
b101101001 4
1'
#82200
0'
#82300
b101101010 4
b11000 2
1'
#82400
0'
#82500
10
03
b0 2
b101101011 4
1'
#82600
0'
#82700
b101101100 4
00
18
07
1'
#82800
0'
#82900
b101101101 4
1'
#83000
0'
#83100
b101101110 4
1'
#83200
0'
#83300
b101101111 4
1'
#83400
0'
#83500
b101110000 4
1'
#83600
0'
#83700
b101110001 4
1'
#83800
0'
#83900
b101110010 4
1'
#84000
0'
#84100
b101110011 4
1'
#84200
0'
#84300
b101110100 4
1'
#84400
0'
#84500
b101110101 4
1'
#84600
0'
#84700
b101110110 4
1'
#84800
0'
#84900
b101110111 4
1'
#85000
0'
#85100
b101111000 4
1'
#85200
0'
#85300
b101111001 4
1'
#85400
0'
#85500
b101111010 4
1'
#85600
0'
#85700
b101111011 4
1'
#85800
0'
#85900
b101111100 4
1'
#86000
0'
#86100
b101111101 4
1'
#86200
0'
#86300
b101111110 4
1'
#86400
0'
#86500
b101111111 4
1'
#86600
0'
#86700
b110000000 4
1'
#86800
0'
#86900
b110000001 4
1'
#87000
0'
0%
#87100
0=
b110000010 4
1'
#87200
0'
#87300
1+
b110000011 4
0>
1'
#87400
0'
#87500
0+
0?
b110000100 4
1'
#87600
0'
#87700
b110000101 4
1'
#87800
0'
#87900
b110000110 4
1'
#88000
0'
1&
#88100
b110000111 4
1@
1'
#88200
0'
#88300
1.
1A
b110001000 4
1'
#88400
0'
#88500
0.
13
b110001001 4
1B
1'
#88600
0'
#88700
b110001010 4
b1 2
1'
#88800
0'
#88900
b10 2
b110001011 4
1'
#89000
0'
#89100
b110001100 4
b11 2
1'
#89200
0'
#89300
b100 2
b110001101 4
1'
#89400
0'
#89500
b110001110 4
b101 2
1'
#89600
0'
#89700
b110 2
b110001111 4
1'
#89800
0'
#89900
b110010000 4
b111 2
1'
#90000
0'
#90100
b1000 2
b110010001 4
1'
#90200
0'
#90300
b110010010 4
b1001 2
1'
#90400
0'
#90500
b1010 2
b110010011 4
1'
#90600
0'
#90700
b110010100 4
b1011 2
1'
#90800
0'
#90900
b1100 2
b110010101 4
1'
#91000
0'
#91100
b110010110 4
b1101 2
1'
#91200
0'
#91300
b1110 2
b110010111 4
1'
#91400
0'
#91500
b110011000 4
b1111 2
1'
#91600
0'
#91700
b10000 2
b110011001 4
1'
#91800
0'
#91900
b110011010 4
b10001 2
1'
#92000
0'
#92100
b10010 2
b110011011 4
1'
#92200
0'
#92300
b110011100 4
b10011 2
1'
#92400
0'
#92500
b10100 2
b110011101 4
1'
#92600
0'
#92700
b110011110 4
b10101 2
1'
#92800
0'
#92900
b10110 2
b110011111 4
1'
#93000
0'
#93100
b110100000 4
b10111 2
1'
#93200
0'
#93300
b11000 2
b110100001 4
1'
#93400
0'
#93500
b110100010 4
b0 2
03
11
1'
#93600
0'
#93700
19
08
01
b110100011 4
1'
#93800
0'
#93900
b110100100 4
1'
#94000
0'
#94100
b110100101 4
1'
#94200
0'
#94300
b110100110 4
1'
#94400
0'
#94500
b110100111 4
1'
#94600
0'
#94700
b110101000 4
1'
#94800
0'
#94900
b110101001 4
1'
#95000
0'
#95100
b110101010 4
1'
#95200
0'
