test/task2_4.v
module task2_4(X, Y, Z, F);
    input X, Y, Z;
    output F;
    wire YN, XN, ZN, XYN, XYNZ, XNYZN;

    not not_XN(XN, X);
    not not_YN(YN, Y);
    not not_ZN(ZN, Z);

    or or_XYN(XYN, X, YN);
    and and_XYNZ(XYNZ, XYN, Z);
    and and_XNYZN(XNYZN, XN, Y, ZN);

    or or_F(F, XYNZ, XNYZN);
endmodule

test/tb_task2_4.v
`timescale 1ns/1ps
`include "task2_4.v"
module tb_task2_4;

    // task2_4 Parameters
    parameter PERIOD = 10;

    // task2_4 Inputs
    reg X = 0;
    reg Y = 0;
    reg Z = 0;

    // task2_4 Outputs
    wire F;

    task2_4 u_task2_4 (
        .X(X),
        .Y(Y),
        .Z(Z),
        .F(F)
    );

    initial begin
        $dumpfile("./wave/tb_task2_4.vcd");
        $dumpvars(0, tb_task2_4);
        #PERIOD;
        X = 0; Y = 0; Z = 0;
        #PERIOD;
        X = 0; Y = 0; Z = 1;
        #PERIOD;
        X = 0; Y = 1; Z = 0;
        #PERIOD;
        X = 0; Y = 1; Z = 1;
        #PERIOD;
        X = 1; Y = 0; Z = 0;
        #PERIOD;
        X = 1; Y = 0; Z = 1;
        #PERIOD;
        X = 1; Y = 1; Z = 0;
        #PERIOD;
        X = 1; Y = 1; Z = 1;
        #PERIOD;
    end

endmodule

test/wave/tb_task2_4.vcd
$date
	Tue Oct 24 09:24:56 2023
$end
$version
	Icarus Verilog
$end
$timescale
	1ps
$end
$scope module tb_task2_4 $end
$var wire 1 ! F $end
$var parameter 32 " PERIOD $end
$var reg 1 # X $end
$var reg 1 $ Y $end
$var reg 1 % Z $end
$scope module u_task2_4 $end
$var wire 1 ! F $end
$var wire 1 # X $end
$var wire 1 & XN $end
$var wire 1 ' XNYZN $end
$var wire 1 ( XYN $end
$var wire 1 ) XYNZ $end
$var wire 1 $ Y $end
$var wire 1 * YN $end
$var wire 1 % Z $end
$var wire 1 + ZN $end
$upscope $end
$upscope $end
$enddefinitions $end
$comment Show the parameter values. $end
$dumpall
b1010 "
$end
#0
$dumpvars
1+
1*
0)
1(
0'
1&
0%
0$
0#
0!
$end
#20000
1!
0+
1)
1%
#30000
1'
1!
0(
1+
0)
0*
0%
1$
#40000
0!
0'
0+
1%
#50000
1+
1*
0&
1(
0%
0$
1#
#60000
1!
0+
1)
1%
#70000
0!
1+
0)
0*
0%
1$
#80000
1!
0+
1)
1%
