test/task2_2.v
module task2_2(A, B, C, X, Y);
    input A, B, C;
    output X, Y;
    wire B_L, A_L, M1_L, M2_L, M3_L, M4_L, M1, M2, M3, M4, M1_LL, M2_LL, M3_LL, M4_LL;

    not U1(A_L, A);
    not U2(B_L, B);
    
    and U3(M1, A, B_L);
    and U4(M2, A_L, B);
    and U5(M3, A_L, C);
    and U6(M4, B, C);

    not U7(M1_L, M1);
    not U8(M2_L, M2);
    not U9(M3_L, M3);
    not U10(M4_L, M4);

    not U11(M1_LL, M1_L);
    not U12(M2_LL, M2_L);
    not U13(M3_LL, M3_L);
    not U14(M4_LL, M4_L);

    or U15(X, M1_LL, M2_LL);
    or U16(Y, M3_LL, M4_LL);
endmodule

test/tb_task2_2.v
`timescale 1ns / 1ps
`include "task2_2.v"
module tb_task2_2;

    // task2_2 Parameters
    parameter PERIOD = 10;

    // task2_2 Inputs
    reg A = 0;
    reg B = 0;
    reg C = 0;

    // task2_2 Outputs
    wire X;
    wire Y;

    task2_2 u_task2_2 (
        .A(A),
        .B(B),
        .C(C),
        .X(X),
        .Y(Y)
    );

    initial begin
        $dumpfile("./wave/tb_task2_2.vcd");
        $dumpvars(0, tb_task2_2);
        A = 0; B = 0; C = 0;
        #PERIOD;
        A = 0; B = 0; C = 1;
        #PERIOD;
        A = 0; B = 1; C = 0;
        #PERIOD;
        A = 0; B = 1; C = 1;
        #PERIOD;
        A = 1; B = 0; C = 0;
        #PERIOD;
        A = 1; B = 0; C = 1;
        #PERIOD;
        A = 1; B = 1; C = 0;
        #PERIOD;
        A = 1; B = 1; C = 1;
        #PERIOD;

    end

endmodule

test/wave/tb_task2_2.vcd
$date
	Wed Oct 25 09:12:29 2023
$end
$version
	Icarus Verilog
$end
$timescale
	1ps
$end
$scope module tb_task2_2 $end
$var wire 1 ! Y $end
$var wire 1 " X $end
$var parameter 32 # PERIOD $end
$var reg 1 $ A $end
$var reg 1 % B $end
$var reg 1 & C $end
$scope module u_task2_2 $end
$var wire 1 $ A $end
$var wire 1 ' A_L $end
$var wire 1 % B $end
$var wire 1 ( B_L $end
$var wire 1 & C $end
$var wire 1 ) M1 $end
$var wire 1 * M1_L $end
$var wire 1 + M1_LL $end
$var wire 1 , M2 $end
$var wire 1 - M2_L $end
$var wire 1 . M2_LL $end
$var wire 1 / M3 $end
$var wire 1 0 M3_L $end
$var wire 1 1 M3_LL $end
$var wire 1 2 M4 $end
$var wire 1 3 M4_L $end
$var wire 1 4 M4_LL $end
$var wire 1 " X $end
$var wire 1 ! Y $end
$upscope $end
$upscope $end
$enddefinitions $end
$comment Show the parameter values. $end
$dumpall
b1010 #
$end
#0
$dumpvars
04
13
02
01
10
0/
0.
1-
0,
0+
1*
0)
1(
1'
0&
0%
0$
0"
0!
$end
#10000
1!
11
00
1/
1&
#20000
0!
1"
01
1.
10
0-
0/
0(
1,
0&
1%
#30000
1!
11
14
00
03
1/
12
1&
#40000
1+
1"
0!
01
0*
0.
04
10
1)
1-
13
0/
1(
0,
02
0'
0&
0%
1$
#50000
1&
#60000
0"
0+
1*
0)
0(
0&
1%
#70000
1!
14
03
12
1&
